[
  {
    "id": 3990,
    "slug": "the-last-of-us",
    "title": "The Last Of Us",
    "year": 2013,
    "coverImage": "https://media.rawg.io/media/games/a5a/a5a7fb8d9cb8063a8b42ee002b410db6.jpg",
    "rawgUrl": "https://rawg.io/games/the-last-of-us",
    "genres": [
      "Adventure",
      "Action"
    ],
    "metacritic": 95,
    "played": true,
    "platform": "PS3",
    "platformType": "PlayStation",
    "datePlayed": "2020-07",
    "completionStatus": "Completed",
    "rating": 10,
    "description": "The best story ever."
  },
  {
    "id": 4544,
    "slug": "red-dead-redemption",
    "title": "Red Dead Redemption",
    "year": 2010,
    "coverImage": "https://media.rawg.io/media/games/686/686909717c3aa01518bc42ae2bf4259e.jpg",
    "rawgUrl": "https://rawg.io/games/red-dead-redemption",
    "genres": [
      "Shooter",
      "Action"
    ],
    "metacritic": 95,
    "played": true,
    "platform": "PS3",
    "platformType": "PlayStation",
    "datePlayed": "2022-04",
    "completionStatus": "Completed",
    "rating": 10,
    "description": "Has a very good story."
  },
  {
    "id": 7439,
    "slug": "call-of-duty-ghosts",
    "title": "Call of Duty: Ghosts",
    "year": 2013,
    "coverImage": "https://media.rawg.io/media/games/eb2/eb24800b4491701eca481e7c990bce4a.jpg",
    "rawgUrl": "https://rawg.io/games/call-of-duty-ghosts",
    "genres": [
      "Shooter",
      "Action"
    ],
    "metacritic": 68,
    "played": true,
    "platform": "PS4",
    "platformType": "PlayStation",
    "datePlayed": "2022-06",
    "completionStatus": "Completed",
    "rating": 8,
    "description": null
  },
  {
    "id": 50778,
    "slug": "a-way-out-2018",
    "title": "A Way Out",
    "year": 2018,
    "coverImage": "https://media.rawg.io/media/games/473/473bd9a5e9522629d6cb28b701fb836a.jpg",
    "rawgUrl": "https://rawg.io/games/a-way-out-2018",
    "genres": [
      "Adventure",
      "Action"
    ],
    "metacritic": 78,
    "played": true,
    "platform": "PS4",
    "platformType": "PlayStation",
    "datePlayed": "2022-06",
    "completionStatus": "Completed",
    "rating": 10,
    "description": "Great finale!"
  },
  {
    "id": 419297,
    "slug": "horizon-zero-dawn-complete-edition",
    "title": "Horizon Zero Dawn Complete Edition",
    "year": 2017,
    "coverImage": "https://media.rawg.io/media/games/d71/d7103d99d17e4b66acd1d6ad746e5bd5.jpg",
    "rawgUrl": "https://rawg.io/games/horizon-zero-dawn-complete-edition",
    "genres": [
      "Adventure",
      "Action",
      "RPG"
    ],
    "metacritic": 84,
    "played": true,
    "platform": "PS4",
    "platformType": "PlayStation",
    "datePlayed": "2022-10",
    "completionStatus": "Completed",
    "rating": 10,
    "description": "Liked the AI philosophy in this game."
  },
  {
    "id": 842,
    "slug": "call-of-duty-advanced-warfare",
    "title": "Call of Duty: Advanced Warfare",
    "year": 2014,
    "coverImage": "https://media.rawg.io/media/games/e05/e053aae547e0978ad90280a1a3d8f177.jpg",
    "rawgUrl": "https://rawg.io/games/call-of-duty-advanced-warfare",
    "genres": [
      "Shooter",
      "Action"
    ],
    "metacritic": 78,
    "played": true,
    "platform": "PS4",
    "platformType": "PlayStation",
    "datePlayed": "2022-10",
    "completionStatus": "Completed",
    "rating": 8,
    "description": null
  },
  {
    "id": 58134,
    "slug": "marvels-spider-man",
    "title": "Marvel's Spider-Man",
    "year": 2018,
    "coverImage": "https://media.rawg.io/media/games/9aa/9aa42d16d425fa6f179fc9dc2f763647.jpg",
    "rawgUrl": "https://rawg.io/games/marvels-spider-man",
    "genres": [
      "Action"
    ],
    "metacritic": 87,
    "played": true,
    "platform": "PS4",
    "platformType": "PlayStation",
    "datePlayed": "2022-11",
    "completionStatus": "Completed",
    "rating": 10,
    "description": "Loved the huge and realistic map."
  },
  {
    "id": 887,
    "slug": "call-of-duty-infinite-warfare",
    "title": "Call of Duty: Infinite Warfare",
    "year": 2016,
    "coverImage": "https://media.rawg.io/media/games/6f7/6f7341dd656910be2c2cda39193a7ec9.jpg",
    "rawgUrl": "https://rawg.io/games/call-of-duty-infinite-warfare",
    "genres": [
      "Shooter",
      "Action"
    ],
    "metacritic": 73,
    "played": true,
    "platform": "PS4",
    "platformType": "PlayStation",
    "datePlayed": "2022-11",
    "completionStatus": "Completed",
    "rating": 8,
    "description": null
  },
  {
    "id": 3137,
    "slug": "uncharted-the-nathan-drake-collection",
    "title": "UNCHARTED The Nathan Drake Collection",
    "year": 2015,
    "coverImage": "https://media.rawg.io/media/games/696/69626956eaf787f5c1b664984279060f.jpg",
    "rawgUrl": "https://rawg.io/games/uncharted-the-nathan-drake-collection",
    "genres": [
      "Adventure",
      "Action"
    ],
    "metacritic": 86,
    "played": true,
    "platform": "PS4",
    "platformType": "PlayStation",
    "datePlayed": "2022-11",
    "completionStatus": "Completed",
    "rating": 10,
    "description": "Good story."
  },
  {
    "id": 58550,
    "slug": "ghost-of-tsushima",
    "title": "Ghost of Tsushima",
    "year": 2020,
    "coverImage": "https://media.rawg.io/media/games/f24/f2493ea338fe7bd3c7d73750a85a0959.jpeg",
    "rawgUrl": "https://rawg.io/games/ghost-of-tsushima",
    "genres": [
      "Adventure",
      "Action",
      "RPG"
    ],
    "metacritic": 83,
    "played": true,
    "platform": "PS4",
    "platformType": "PlayStation",
    "datePlayed": "2022-12",
    "completionStatus": "Completed",
    "rating": 10,
    "description": "Great story, map and details."
  },
  {
    "id": 3254,
    "slug": "journey",
    "title": "Journey",
    "year": 2012,
    "coverImage": "https://media.rawg.io/media/games/baf/baf9905270314e07e6850cffdb51df41.jpg",
    "rawgUrl": "https://rawg.io/games/journey",
    "genres": [
      "Family",
      "Indie",
      "Adventure"
    ],
    "metacritic": 92,
    "played": true,
    "platform": "PS4",
    "platformType": "PlayStation",
    "datePlayed": "2022-12",
    "completionStatus": "Completed",
    "rating": 7,
    "description": "A unique experience. Liked the solo journey."
  },
  {
    "id": 3636,
    "slug": "the-last-of-us-remastered",
    "title": "The Last Of Us Remastered",
    "year": 2014,
    "coverImage": "https://media.rawg.io/media/games/364/3642d850efb217c58feab80b8affaa89.jpg",
    "rawgUrl": "https://rawg.io/games/the-last-of-us-remastered",
    "genres": [
      "Adventure",
      "Action"
    ],
    "metacritic": 95,
    "played": true,
    "platform": "PS4",
    "platformType": "PlayStation",
    "datePlayed": "2023-01",
    "completionStatus": "Completed",
    "rating": 10,
    "description": "The best story ever."
  },
  {
    "id": 50738,
    "slug": "death-stranding",
    "title": "Death Stranding",
    "year": 2019,
    "coverImage": "https://media.rawg.io/media/games/2ad/2ad87a4a69b1104f02435c14c5196095.jpg",
    "rawgUrl": "https://rawg.io/games/death-stranding",
    "genres": [
      "Adventure",
      "Action"
    ],
    "metacritic": 84,
    "played": true,
    "platform": "PS4",
    "platformType": "PlayStation",
    "datePlayed": "2023-01",
    "completionStatus": "Completed",
    "rating": 10,
    "description": "Very creative story, world and play style."
  },
  {
    "id": 51325,
    "slug": "the-last-of-us-part-2",
    "title": "The Last of Us Part II",
    "year": 2020,
    "coverImage": "https://media.rawg.io/media/games/909/909974d1c7863c2027241e265fe7011f.jpg",
    "rawgUrl": "https://rawg.io/games/the-last-of-us-part-2",
    "genres": [
      "Shooter",
      "Adventure",
      "Action"
    ],
    "metacritic": 93,
    "played": true,
    "platform": "PS4",
    "platformType": "PlayStation",
    "datePlayed": "2023-02",
    "completionStatus": "Completed",
    "rating": 10,
    "description": "Better story than the first game. The ending was amazing. It left me conflicted about my own thoughts and decisions."
  },
  {
    "id": 41494,
    "slug": "cyberpunk-2077",
    "title": "Cyberpunk 2077",
    "year": 2020,
    "coverImage": "https://media.rawg.io/media/games/26d/26d4437715bee60138dab4a7c8c59c92.jpg",
    "rawgUrl": "https://rawg.io/games/cyberpunk-2077",
    "genres": [
      "Shooter",
      "Action",
      "RPG"
    ],
    "metacritic": 73,
    "played": true,
    "platform": "PS5",
    "platformType": "PlayStation",
    "datePlayed": "2023-02",
    "completionStatus": "Completed",
    "rating": 10,
    "description": "Excellent game. Played it three times and used save files to see every ending. The story is fantastic, and its take on capitalism is one of the strongest parts of the game."
  },
  {
    "id": 452634,
    "slug": "marvels-spider-man-miles-morales",
    "title": "Marvel's Spider-Man: Miles Morales",
    "year": 2020,
    "coverImage": "https://media.rawg.io/media/games/048/048b46cdc66cbc7e235e1f359c2a77ec.jpg",
    "rawgUrl": "https://rawg.io/games/marvels-spider-man-miles-morales",
    "genres": [
      "Action"
    ],
    "metacritic": 86,
    "played": true,
    "platform": "PS5",
    "platformType": "PlayStation",
    "datePlayed": "2023-04",
    "completionStatus": "Completed",
    "rating": 9,
    "description": "Same as the first game in the series, I liked the map, story, and attention to detail. The only downside is that it felt too short."
  },
  {
    "id": 452646,
    "slug": "astros-playroom",
    "title": "Astro's Playroom",
    "year": 2020,
    "coverImage": "https://media.rawg.io/media/games/bfe/bfe7780b7d4342540be2e5273d49e54c.jpg",
    "rawgUrl": "https://rawg.io/games/astros-playroom",
    "genres": [
      "Platformer",
      "Action"
    ],
    "metacritic": 83,
    "played": true,
    "platform": "PS5",
    "platformType": "PlayStation",
    "datePlayed": "2023-04",
    "completionStatus": "Completed",
    "rating": 6,
    "description": "Shows off DualSense features, and gives a quick Playstation history recap. Creative but not an amazing game."
  },
  {
    "id": 2462,
    "slug": "uncharted-4-a-thiefs-end",
    "title": "Uncharted 4: A Thief's End",
    "year": 2016,
    "coverImage": "https://media.rawg.io/media/games/709/709bf81f874ce5d25d625b37b014cb63.jpg",
    "rawgUrl": "https://rawg.io/games/uncharted-4-a-thiefs-end",
    "genres": [
      "Shooter",
      "Action"
    ],
    "metacritic": 93,
    "played": true,
    "platform": "PS5",
    "platformType": "PlayStation",
    "datePlayed": "2023-05",
    "completionStatus": "Completed",
    "rating": 10,
    "description": "Great story. Loved seeing Drake and his brother Sam's past."
  },
  {
    "id": 3209,
    "slug": "until-dawn",
    "title": "Until Dawn",
    "year": 2015,
    "coverImage": "https://media.rawg.io/media/games/d64/d6443375f9971152866ea76bff97d6d6.jpg",
    "rawgUrl": "https://rawg.io/games/until-dawn",
    "genres": [
      "Adventure",
      "Action"
    ],
    "metacritic": 79,
    "played": true,
    "platform": "PS5",
    "platformType": "PlayStation",
    "datePlayed": "2023-05",
    "completionStatus": "Completed",
    "rating": 9,
    "description": "Good horror game. It wasn't that scary but I loved how the choices affected the story."
  },
  {
    "id": 480,
    "slug": "resident-evil-7-biohazard",
    "title": "Resident Evil 7: Biohazard",
    "year": 2017,
    "coverImage": "https://media.rawg.io/media/games/cee/cee577e2097a59b77193fe2bce94667d.jpg",
    "rawgUrl": "https://rawg.io/games/resident-evil-7-biohazard",
    "genres": [
      "Shooter",
      "Adventure",
      "Action"
    ],
    "metacritic": 85,
    "played": true,
    "platform": "PS5",
    "platformType": "PlayStation",
    "datePlayed": "2023-06",
    "completionStatus": "Completed",
    "rating": 10,
    "description": "Amazing game. Loved the graphics, the story and the game play. Scariest game I played."
  },
  {
    "id": 29338,
    "slug": "days-gone",
    "title": "Days Gone",
    "year": 2019,
    "coverImage": "https://media.rawg.io/media/games/a79/a79d2fc90c4dbf07a8580b19600fd61d.jpg",
    "rawgUrl": "https://rawg.io/games/days-gone",
    "genres": [
      "Action"
    ],
    "metacritic": 74,
    "played": true,
    "platform": "PS5",
    "platformType": "PlayStation",
    "datePlayed": "2023-07",
    "completionStatus": "Completed",
    "rating": 10,
    "description": "Great open world action game. Good story too."
  },
  {
    "id": 2553,
    "slug": "ratchet-clank",
    "title": "Ratchet & Clank",
    "year": 2016,
    "coverImage": "https://media.rawg.io/media/games/d30/d30ef0c7dd4878161b1f781e297ae6a0.jpg",
    "rawgUrl": "https://rawg.io/games/ratchet-clank",
    "genres": [
      "Action",
      "Adventure",
      "Platformer"
    ],
    "metacritic": 85,
    "played": true,
    "platform": "PS5",
    "platformType": "PlayStation",
    "datePlayed": "2023-07",
    "completionStatus": "Completed",
    "rating": 5,
    "description": "Not my type."
  },
  {
    "id": 397473,
    "slug": "back-4-blood",
    "title": "Back 4 Blood",
    "year": 2021,
    "coverImage": "https://media.rawg.io/media/games/4fe/4feffcec6315c5f5a96442a8444431ca.jpg",
    "rawgUrl": "https://rawg.io/games/back-4-blood",
    "genres": [
      "Shooter",
      "Action"
    ],
    "metacritic": 76,
    "played": true,
    "platform": "PS5",
    "platformType": "PlayStation",
    "datePlayed": "2023-08",
    "completionStatus": "Completed",
    "rating": 8,
    "description": null
  },
  {
    "id": 647552,
    "slug": "call-of-duty-vanguard",
    "title": "Call of Duty: Vanguard",
    "year": 2021,
    "coverImage": "https://media.rawg.io/media/games/fa8/fa870a46d5e3e8cb1fa0a5e4f798ff2a.jpg",
    "rawgUrl": "https://rawg.io/games/call-of-duty-vanguard",
    "genres": [
      "Shooter"
    ],
    "metacritic": null,
    "played": true,
    "platform": "PS5",
    "platformType": "PlayStation",
    "datePlayed": "2023-08",
    "completionStatus": "Completed",
    "rating": 10,
    "description": null
  },
  {
    "id": 58831,
    "slug": "call-of-cthulhu-the-official-video-game",
    "title": "Call of Cthulhu",
    "year": 2018,
    "coverImage": "https://media.rawg.io/media/games/1b8/1b8a3ed646ccea6375bd4d4b7dd67aa4.jpg",
    "rawgUrl": "https://rawg.io/games/call-of-cthulhu-the-official-video-game",
    "genres": [
      "Adventure",
      "Action",
      "RPG"
    ],
    "metacritic": 66,
    "played": true,
    "platform": "PS5",
    "platformType": "PlayStation",
    "datePlayed": "2023-08",
    "completionStatus": "Completed",
    "rating": 9,
    "description": "Good story. First Lovecraftian game I ever played and I liked it."
  },
  {
    "id": 50576,
    "slug": "atomic-heart",
    "title": "Atomic Heart",
    "year": 2023,
    "coverImage": "https://media.rawg.io/media/games/6ee/6ee5cbe30c6b6c299a3288337d40a0f3.jpg",
    "rawgUrl": "https://rawg.io/games/atomic-heart",
    "genres": [
      "Shooter",
      "Adventure",
      "Action"
    ],
    "metacritic": 73,
    "played": true,
    "platform": "PS5",
    "platformType": "PlayStation",
    "datePlayed": "2023-09",
    "completionStatus": "Completed",
    "rating": 7,
    "description": "I agree with the popular thought on this game being very similar to BioShock with its gameplay. I liked the world though."
  },
  {
    "id": 516111,
    "slug": "mass-effect-legendary-edition",
    "title": "Mass Effect: Legendary Edition",
    "year": 2021,
    "coverImage": "https://media.rawg.io/media/games/64e/64e2a77f37ddc48d102127234af99886.jpg",
    "rawgUrl": "https://rawg.io/games/mass-effect-legendary-edition",
    "genres": [
      "Shooter",
      "Adventure",
      "Action",
      "RPG"
    ],
    "metacritic": 88,
    "played": true,
    "platform": "PS5",
    "platformType": "PlayStation",
    "datePlayed": "2023-10",
    "completionStatus": "Completed",
    "rating": 10,
    "description": "Excellent game. The game makes the player bond with the characters well. Has a great ending as well, answers all the questions.\n\n脙聝脗聝脙聜脗聝脙聝脗聜脙聜脗聝脙聝脗聝脙聜脗聜脙聝脗聜脙聜脗聝脙聝脗聝脙聜脗聝脙聝脗聜脙聜脗聜脙聝脗聝脙聜脗聜脙聝脗聜脙聜脗聝脙聝脗聝脙聜脗聝脙聝脗聜脙聜脗聝脙聝脗聝脙聜脗聜脙聝脗聜脙聜脗聜脙聝脗聝脙聜脗聝脙聝脗聜脙聜脗聜脙聝脗聝脙聜脗聜脙聝脗聜脙聜脗聝脙聝脗聝脙聜脗聝脙聝脗聜脙聜脗聝脙聝脗聝脙聜脗聜脙聝脗聜脙聜脗聝脙聝脗聝脙聜脗聝脙聝脗聜脙聜脗聜脙聝脗聝脙聜脗聜脙聝脗聜脙聜脗聜脙聝脗聝脙聜脗聝脙聝脗聜脙聜脗聝脙聝脗聝脙聜脗聜脙聝脗聜脙聜脗聜脙聝脗聝脙聜脗聝脙聝脗聜脙聜脗聜脙聝脗聝脙聜脗聜脙聝脗聜脙聜脗聝脙聝脗聝脙聜脗聝脙聝脗聜脙聜脗聝脙聝脗聝脙聜脗聜脙聝脗聜脙聜脗聝脙聝脗聝脙聜脗聝脙聝脗聜脙聜脗聜脙聝脗聝脙聜脗聜脙聝脗聜脙聜脗聝脙聝脗聝脙聜脗聝脙聝脗聜脙聜脗聝脙聝脗聝脙聜脗聜脙聝脗聜脙聜脗聜脙聝脗聝脙聜脗聝脙聝脗聜脙聜脗聜脙聝脗聝脙聜脗聜脙聝脗聜脙聜脗聜脙聝脗聝脙聜脗聝脙聝脗聜脙聜脗聝脙聝脗聝脙聜脗聜脙聝脗聜脙聜脗聝脙聝脗聝脙聜脗聝脙聝脗聜脙聜脗聜脙聝脗聝脙聜脗聜脙聝脗聜脙聜脗聜脙聝脗聝脙聜脗聝脙聝脗聜脙聜脗聝脙聝脗聝脙聜脗聜脙聝脗聜脙聜脗聜脙聝脗聝脙聜脗聝脙聝脗聜脙聜脗聜脙聝脗聝脙聜脗聜脙聝脗聜脙聜脗聝脙聝脗聝脙聜脗聝脙聝脗聜脙聜脗聝脙聝脗聝脙聜脗聜脙聝脗聜脙聜脗聝脙聝脗聝脙聜脗聝脙聝脗聜脙聜脗聜脙聝脗聝脙聜脗聜脙聝脗聜脙聜脗聝脙聝脗聝脙聜脗聝脙聝脗聜脙聜脗聝脙聝脗聝脙聜脗聜脙聝脗聜脙聜脗聜脙聝脗聝脙聜脗聝脙聝脗聜脙聜脗聜脙聝脗聝脙聜脗聜脙聝脗聜脙聜脗聝脙聝脗聝脙聜脗聝脙聝脗聜脙聜脗聝脙聝脗聝脙聜脗聜脙聝脗聜脙聜脗聝脙聝脗聝脙聜脗聝脙聝脗聜脙聜脗聜脙聝脗聝脙聜脗聜脙聝脗聜脙聜脗聜脙聝脗聝脙聜脗聝脙聝脗聜脙聜脗聝脙聝脗聝脙聜脗聜脙聝脗聜脙聜脗聜脙聝脗聝脙聜脗聝脙聝脗聜脙聜脗聜脙聝脗聝脙聜脗聜脙聝脗聜脙聜脗聜脙聝脗聝脙聜脗聝脙聝脗聜脙聜脗聝脙聝脗聝脙聜脗聜脙聝脗聜脙聜脗聝脙聝脗聝脙聜脗聝脙聝脗聜脙聜脗聜脙聝脗聝脙聜脗聜脙聝脗聜脙聜脗聝脙聝脗聝脙聜脗聝脙聝脗聜脙聜脗聝脙聝脗聝脙聜脗聜脙聝脗聜脙聜脗聜脙聝脗聝脙聜脗聝脙聝脗聜脙聜脗聜脙聝脗聝脙聜脗聜脙聝脗聜脙聜脗聜脙聝脗聝脙聜脗聝脙聝脗聜脙聜脗聝脙聝脗聝脙聜脗聜脙聝脗聜脙聜脗聝脙聝脗聝脙聜脗聝脙聝脗聜脙聜脗聜脙聝脗聝脙聜脗聜脙聝脗聜脙聜脗聜脙聝脗聝脙聜脗聝脙聝脗聜脙聜脗聝脙聝脗聝脙聜脗聜脙聝脗聜脙聜脗聜脙聝脗聝脙聜脗聝脙聝脗聜脙聜脗聜脙聝脗聝脙聜脗聜脙聝脗聜脙聜脗聝脙聝脗聝脙聜脗聝脙聝脗聜脙聜脗聝脙聝脗聝脙聜脗聜脙聝脗聜脙聜脗聝脙聝脗聝脙聜脗聝脙聝脗聜脙聜脗聜脙聝脗聝脙聜脗聜脙聝脗聜脙聜脗聝脙聝脗聝脙聜脗聝脙聝脗聜脙聜脗聝脙聝脗聝脙聜脗聜脙聝脗聜脙聜脗聜脙聝脗聝脙聜脗聝脙聝脗聜脙聜脗聜脙聝脗聝脙聜脗聜脙聝脗聜脙聜脗聝脙聝脗聝脙聜脗聝脙聝脗聜脙聜脗聝脙聝脗聝脙聜脗聜脙聝脗聜脙聜脗聝脙聝脗聝脙聜脗聝脙聝脗聜脙聜脗聜脙聝脗聝脙聜脗聜脙聝脗聜脙聜脗聜脙聝脗聝脙聜脗聝脙聝脗聜脙聜脗聝脙聝脗聝脙聜脗聜脙聝脗聜脙聜脗聜脙聝脗聝脙聜脗聝脙聝脗聜脙聜脗聜脙聝脗聝脙聜脗聜脙聝脗聜脙聜脗聝脙聝脗聝脙聜脗聝脙聝脗聜脙聜脗聝脙聝脗聝脙聜脗聜脙聝脗聜脙聜脗聝脙聝脗聝脙聜脗聝脙聝脗聜脙聜脗聜脙聝脗聝脙聜脗聜脙聝脗聜脙聜脗聝脙聝脗聝脙聜脗聝脙聝脗聜脙聜脗聝脙聝脗聝脙聜脗聜脙聝脗聜脙聜脗聜脙聝脗聝脙聜脗聝脙聝脗聜脙聜脗聜脙聝脗聝脙聜脗聜脙聝脗聜脙聜脗聜脙聝脗聝脙聜脗聝脙聝脗聜脙聜脗聝脙聝脗聝脙聜脗聜脙聝脗聜脙聜脗聝脙聝脗聝脙聜脗聝脙聝脗聜脙聜脗聜脙聝脗聝脙聜脗聜脙聝脗聜脙聜脗聜脙聝脗聝脙聜脗聝脙聝脗聜脙聜脗聝脙聝脗聝脙聜脗聜脙聝脗聜脙聜脗聜脙聝脗聝脙聜脗聝脙聝脗聜脙聜脗聜脙聝脗聝脙聜脗聜脙聝脗聜脙聜脗聜脙聝脗聝脙聜脗聝脙聝脗聜脙聜脗聝脙聝脗聝脙聜脗聜脙聝脗聜脙聜脗聝脙聝脗聝脙聜脗聝脙聝脗聜脙聜脗聜脙聝脗聝脙聜脗聜脙聝脗聜脙聜脗聝脙聝脗聝脙聜脗聝脙聝脗聜脙聜脗聝脙聝脗聝脙聜脗聜脙聝脗聜脙聜脗聜脙聝脗聝脙聜脗聝脙聝脗聜脙聜脗聜脙聝脗聝脙聜脗聜脙聝脗聜脙聜脗聝脙聝脗聝脙聜脗聝脙聝脗聜脙聜脗聝脙聝脗聝脙聜脗聜脙聝脗聜脙聜脗聝脙聝脗聝脙聜脗聝脙聝脗聜脙聜脗聜脙聝脗聝脙聜脗聜脙聝脗聜脙聜脗聜脙聝脗聝脙聜脗聝脙聝脗聜脙聜脗聝脙聝脗聝脙聜脗聜脙聝脗聜脙聜脗聜脙聝脗聝脙聜脗聝脙聝脗聜脙聜脗聜脙聝脗聝脙聜脗聜脙聝脗聜脙聜脗聜脙聝脗聝脙聜脗聝脙聝脗聜脙聜脗聝脙聝脗聝脙聜脗聜脙聝脗聜脙聜脗聝脙聝脗聝脙聜脗聝脙聝脗聜脙聜脗聜脙聝脗聝脙聜脗聜脙聝脗聜脙聜脗聝脙聝脗聝脙聜脗聝脙聝脗聜脙聜脗聝脙聝脗聝脙聜脗聜脙聝脗聜脙聜脗聜脙聝脗聝脙聜脗聝脙聝脗聜脙聜脗聜脙聝脗聝脙聜脗聜脙聝脗聜脙聜脗聜脙聝脗聝脙聜脗聝脙聝脗聜脙聜脗聝脙聝脗聝脙聜脗聜脙聝脗聜脙聜脗聝脙聝脗聝脙聜脗聝脙聝脗聜脙聜脗聜脙聝脗聝脙聜脗聜脙聝脗聜脙聜脗聜脙聝脗聝脙聜脗聝脙聝脗聜脙聜脗聝脙聝脗聝脙聜脗聜脙聝脗聜脙聜脗聜脙聝脗聝脙聜脗聝脙聝脗聜脙聜脗聜脙聝脗聝脙聜脗聜脙聝脗聜脙聜脗垄脙聝脗聝脙聜脗聝脙聝脗聜脙聜脗聝脙聝脗聝脙聜脗聜脙聝脗聜脙聜脗聝脙聝脗聝脙聜脗聝脙聝脗聜脙聜脗聜脙聝脗聝脙聜脗聜脙聝脗聜脙聜脗聝脙聝脗聝脙聜脗聝脙聝脗聜脙聜脗聝脙聝脗聝脙聜脗聜脙聝脗聜脙聜脗聜脙聝脗聝脙聜脗聝脙聝脗聜脙聜脗聜脙聝脗聝脙聜脗聜脙聝脗聜脙聜脗聝脙聝脗聝脙聜脗聝脙聝脗聜脙聜脗聝脙聝脗聝脙聜脗聜脙聝脗聜脙聜脗聝脙聝脗聝脙聜脗聝脙聝脗聜脙聜脗聜脙聝脗聝脙聜脗聜脙聝脗聜脙聜脗聜脙聝脗聝脙聜脗聝脙聝脗聜脙聜脗聝脙聝脗聝脙聜脗聜脙聝脗聜脙聜脗聜脙聝脗聝脙聜脗聝脙聝脗聜脙聜脗聜脙聝脗聝脙聜脗聜脙聝脗聜脙聜脗聝脙聝脗聝脙聜脗聝脙聝脗聜脙聜脗聝脙聝脗聝脙聜脗聜脙聝脗聜脙聜脗聝脙聝脗聝脙聜脗聝脙聝脗聜脙聜脗聜脙聝脗聝脙聜脗聜脙聝脗聜脙聜脗聝脙聝脗聝脙聜脗聝脙聝脗聜脙聜脗聝脙聝脗聝脙聜脗聜脙聝脗聜脙聜脗聜脙聝脗聝脙聜脗聝脙聝脗聜脙聜脗聜脙聝脗聝脙聜脗聜脙聝脗聜脙聜脗聜脙聝脗聝脙聜脗聝脙聝脗聜脙聜脗聝脙聝脗聝脙聜脗聜脙聝脗聜脙聜脗聝脙聝脗聝脙聜脗聝脙聝脗聜脙聜脗聜脙聝脗聝脙聜脗聜脙聝脗聜脙聜脗聜脙聝脗聝脙聜脗聝脙聝脗聜脙聜脗聝脙聝脗聝脙聜脗聜脙聝脗聜脙聜脗聜脙聝脗聝脙聜脗聝脙聝脗聜脙聜脗聜脙聝脗聝脙聜脗聜脙聝脗聜脙聜脗聝脙聝脗聝脙聜脗聝脙聝脗聜脙聜脗聝脙聝脗聝脙聜脗聜脙聝脗聜脙聜脗聝脙聝脗聝脙聜脗聝脙聝脗聜脙聜脗聜脙聝脗聝脙聜脗聜脙聝脗聜脙聜脗聝脙聝脗聝脙聜脗聝脙聝脗聜脙聜脗聝脙聝脗聝脙聜脗聜脙聝脗聜脙聜脗聜脙聝脗聝脙聜脗聝脙聝脗聜脙聜脗聜脙聝脗聝脙聜脗聜脙聝脗聜脙聜脗聝脙聝脗聝脙聜脗聝脙聝脗聜脙聜脗聝脙聝脗聝脙聜脗聜脙聝脗聜脙聜脗聝脙聝脗聝脙聜脗聝脙聝脗聜脙聜脗聜脙聝脗聝脙聜脗聜脙聝脗聜脙聜脗聜脙聝脗聝脙聜脗聝脙聝脗聜脙聜脗聝脙聝脗聝脙聜脗聜脙聝脗聜脙聜脗聜脙聝脗聝脙聜脗聝脙聝脗聜脙聜脗聜脙聝脗聝脙聜脗聜脙聝脗聜脙聜脗聜脙聝脗聝脙聜脗聝脙聝脗聜脙聜脗聝脙聝脗聝脙聜脗聜脙聝脗聜脙聜脗聝脙聝脗聝脙聜脗聝脙聝脗聜脙聜脗聜脙聝脗聝脙聜脗聜脙聝脗聜脙聜脗聝脙聝脗聝脙聜脗聝脙聝脗聜脙聜脗聝脙聝脗聝脙聜脗聜脙聝脗聜脙聜脗聜脙聝脗聝脙聜脗聝脙聝脗聜脙聜脗聜脙聝脗聝脙聜脗聜脙聝脗聜脙聜脗聜脙聝脗聝脙聜脗聝脙聝脗聜脙聜脗聝脙聝脗聝脙聜脗聜脙聝脗聜脙聜脗聝脙聝脗聝脙聜脗聝脙聝脗聜脙聜脗聜脙聝脗聝脙聜脗聜脙聝脗聜脙聜脗聜脙聝脗聝脙聜脗聝脙聝脗聜脙聜脗聝脙聝脗聝脙聜脗聜脙聝脗聜脙聜脗聜脙聝脗聝脙聜脗聝脙聝脗聜脙聜脗聜脙聝脗聝脙聜脗聜脙聝脗聜脙聜脗聜脙聝脗聝脙聜脗聝脙聝脗聜脙聜脗聝脙聝脗聝脙聜脗聜脙聝脗聜脙聜脗聝脙聝脗聝脙聜脗聝脙聝脗聜脙聜脗聜脙聝脗聝脙聜脗聜脙聝脗聜脙聜脗聝脙聝脗聝脙聜脗聝脙聝脗聜脙聜脗聝脙聝脗聝脙聜脗聜脙聝脗聜脙聜脗聜脙聝脗聝脙聜脗聝脙聝脗聜脙聜脗聜脙聝脗聝脙聜脗聜脙聝脗聜脙聜脗聝脙聝脗聝脙聜脗聝脙聝脗聜脙聜脗聝脙聝脗聝脙聜脗聜脙聝脗聜脙聜脗聝脙聝脗聝脙聜脗聝脙聝脗聜脙聜脗聜脙聝脗聝脙聜脗聜脙聝脗聜脙聜脗聜脙聝脗聝脙聜脗聝脙聝脗聜脙聜脗聝脙聝脗聝脙聜脗聜脙聝脗聜脙聜脗聜脙聝脗聝脙聜脗聝脙聝脗聜脙聜脗聜脙聝脗聝脙聜脗聜脙聝脗聜脙聜脗聝脙聝脗聝脙聜脗聝脙聝脗聜脙聜脗聝脙聝脗聝脙聜脗聜脙聝脗聜脙聜脗聝脙聝脗聝脙聜脗聝脙聝脗聜脙聜脗聜脙聝脗聝脙聜脗聜脙聝脗聜脙聜脗聝脙聝脗聝脙聜脗聝脙聝脗聜脙聜脗聝脙聝脗聝脙聜脗聜脙聝脗聜脙聜脗聜脙聝脗聝脙聜脗聝脙聝脗聜脙聜脗聜脙聝脗聝脙聜脗聜脙聝脗聜脙聜脗聜脙聝脗聝脙聜脗聝脙聝脗聜脙聜脗聝脙聝脗聝脙聜脗聜脙聝脗聜脙聜脗聝脙聝脗聝脙聜脗聝脙聝脗聜脙聜脗聜脙聝脗聝脙聜脗聜脙聝脗聜脙聜脗聜脙聝脗聝脙聜脗聝脙聝脗聜脙聜脗聝脙聝脗聝脙聜脗聜脙聝脗聜脙聜脗聜脙聝脗聝脙聜脗聝脙聝脗聜脙聜脗聜脙聝脗聝脙聜脗聜脙聝脗聜脙聜脗聜脙聝脗聝脙聜脗聝脙聝脗聜脙聜脗聝脙聝脗聝脙聜脗聜脙聝脗聜脙聜脗聝脙聝脗聝脙聜脗聝脙聝脗聜脙聜脗聜脙聝脗聝脙聜脗聜脙聝脗聜脙聜脗聝脙聝脗聝脙聜脗聝脙聝脗聜脙聜脗聝脙聝脗聝脙聜脗聜脙聝脗聜脙聜脗聜脙聝脗聝脙聜脗聝脙聝脗聜脙聜脗聜脙聝脗聝脙聜脗聜脙聝脗聜脙聜脗聝脙聝脗聝脙聜脗聝脙聝脗聜脙聜脗聝脙聝脗聝脙聜脗聜脙聝脗聜脙聜脗聝脙聝脗聝脙聜脗聝脙聝脗聜脙聜脗聜脙聝脗聝脙聜脗聜脙聝脗聜脙聜脗聜脙聝脗聝脙聜脗聝脙聝脗聜脙聜脗聝脙聝脗聝脙聜脗聜脙聝脗聜脙聜脗聜脙聝脗聝脙聜脗聝脙聝脗聜脙聜脗聜脙聝脗聝脙聜脗聜脙聝脗聜脙聜脗聜脙聝脗聝脙聜脗聝脙聝脗聜脙聜脗聝脙聝脗聝脙聜脗聜脙聝脗聜脙聜脗聝脙聝脗聝脙聜脗聝脙聝脗聜脙聜脗聜脙聝脗聝脙聜脗聜脙聝脗聜脙聜脗聝脙聝脗聝脙聜脗聝脙聝脗聜脙聜脗聝脙聝脗聝脙聜脗聜脙聝脗聜脙聜脗聜脙聝脗聝脙聜脗聝脙聝脗聜脙聜脗聜脙聝脗聝脙聜脗聜脙聝脗聜脙聜脗聜脙聝脗聝脙聜脗聝脙聝脗聜脙聜脗聝脙聝脗聝脙聜脗聜脙聝脗聜脙聜脗聝脙聝脗聝脙聜脗聝脙聝脗聜脙聜脗聜脙聝脗聝脙聜脗聜脙聝脗聜脙聜脗聜脙聝脗聝脙聜脗聝脙聝脗聜脙聜脗聝脙聝脗聝脙聜脗聜脙聝脗聜脙聜脗聜脙聝脗聝脙聜脗聝脙聝脗聜脙聜脗聜脙聝脗聝脙聜脗聜脙聝脗聜脙聜脗聙脙聝脗聝脙聜脗聝脙聝脗聜脙聜脗聝脙聝脗聝脙聜脗聜脙聝脗聜脙聜脗聝脙聝脗聝脙聜脗聝脙聝脗聜脙聜脗聜脙聝脗聝脙聜脗聜脙聝脗聜脙聜脗聝脙聝脗聝脙聜脗聝脙聝脗聜脙聜脗聝脙聝脗聝脙聜脗聜脙聝脗聜脙聜脗聜脙聝脗聝脙聜脗聝脙聝脗聜脙聜脗聜脙聝脗聝脙聜脗聜脙聝脗聜脙聜脗聝脙聝脗聝脙聜脗聝脙聝脗聜脙聜脗聝脙聝脗聝脙聜脗聜脙聝脗聜脙聜脗聝脙聝脗聝脙聜脗聝脙聝脗聜脙聜脗聜脙聝脗聝脙聜脗聜脙聝脗聜脙聜脗聜脙聝脗聝脙聜脗聝脙聝脗聜脙聜脗聝脙聝脗聝脙聜脗聜脙聝脗聜脙聜脗聜脙聝脗聝脙聜脗聝脙聝脗聜脙聜脗聜脙聝脗聝脙聜脗聜脙聝脗聜脙聜脗聝脙聝脗聝脙聜脗聝脙聝脗聜脙聜脗聝脙聝脗聝脙聜脗聜脙聝脗聜脙聜脗聝脙聝脗聝脙聜脗聝脙聝脗聜脙聜脗聜脙聝脗聝脙聜脗聜脙聝脗聜脙聜脗聝脙聝脗聝脙聜脗聝脙聝脗聜脙聜脗聝脙聝脗聝脙聜脗聜脙聝脗聜脙聜脗聜脙聝脗聝脙聜脗聝脙聝脗聜脙聜脗聜脙聝脗聝脙聜脗聜脙聝脗聜脙聜脗聜脙聝脗聝脙聜脗聝脙聝脗聜脙聜脗聝脙聝脗聝脙聜脗聜脙聝脗聜脙聜脗聝脙聝脗聝脙聜脗聝脙聝脗聜脙聜脗聜脙聝脗聝脙聜脗聜脙聝脗聜脙聜脗聜脙聝脗聝脙聜脗聝脙聝脗聜脙聜脗聝脙聝脗聝脙聜脗聜脙聝脗聜脙聜脗聜脙聝脗聝脙聜脗聝脙聝脗聜脙聜脗聜脙聝脗聝脙聜脗聜脙聝脗聜脙聜脗聝脙聝脗聝脙聜脗聝脙聝脗聜脙聜脗聝脙聝脗聝脙聜脗聜脙聝脗聜脙聜脗聝脙聝脗聝脙聜脗聝脙聝脗聜脙聜脗聜脙聝脗聝脙聜脗聜脙聝脗聜脙聜脗聝脙聝脗聝脙聜脗聝脙聝脗聜脙聜脗聝脙聝脗聝脙聜脗聜脙聝脗聜脙聜脗聜脙聝脗聝脙聜脗聝脙聝脗聜脙聜脗聜脙聝脗聝脙聜脗聜脙聝脗聜脙聜脗聝脙聝脗聝脙聜脗聝脙聝脗聜脙聜脗聝脙聝脗聝脙聜脗聜脙聝脗聜脙聜脗聝脙聝脗聝脙聜脗聝脙聝脗聜脙聜脗聜脙聝脗聝脙聜脗聜脙聝脗聜脙聜脗聜脙聝脗聝脙聜脗聝脙聝脗聜脙聜脗聝脙聝脗聝脙聜脗聜脙聝脗聜脙聜脗聜脙聝脗聝脙聜脗聝脙聝脗聜脙聜脗聜脙聝脗聝脙聜脗聜脙聝脗聜脙聜脗聜脙聝脗聝脙聜脗聝脙聝脗聜脙聜脗聝脙聝脗聝脙聜脗聜脙聝脗聜脙聜脗聝脙聝脗聝脙聜脗聝脙聝脗聜脙聜脗聜脙聝脗聝脙聜脗聜脙聝脗聜脙聜脗聝脙聝脗聝脙聜脗聝脙聝脗聜脙聜脗聝脙聝脗聝脙聜脗聜脙聝脗聜脙聜脗聜脙聝脗聝脙聜脗聝脙聝脗聜脙聜脗聜脙聝脗聝脙聜脗聜脙聝脗聜脙聜脗聜脙聝脗聝脙聜脗聝脙聝脗聜脙聜脗聝脙聝脗聝脙聜脗聜脙聝脗聜脙聜脗聝脙聝脗聝脙聜脗聝脙聝脗聜脙聜脗聜脙聝脗聝脙聜脗聜脙聝脗聜脙聜脗聜脙聝脗聝脙聜脗聝脙聝脗聜脙聜脗聝脙聝脗聝脙聜脗聜脙聝脗聜脙聜脗聜脙聝脗聝脙聜脗聝脙聝脗聜脙聜脗聜脙聝脗聝脙聜脗聜脙聝脗聜脙聜脗聜脙聝脗聝脙聜脗聝脙聝脗聜脙聜脗聝脙聝脗聝脙聜脗聜脙聝脗聜脙聜脗聝脙聝脗聝脙聜脗聝脙聝脗聜脙聜脗聜脙聝脗聝脙聜脗聜脙聝脗聜脙聜脗聝脙聝脗聝脙聜脗聝脙聝脗聜脙聜脗聝脙聝脗聝脙聜脗聜脙聝脗聜脙聜脗聜脙聝脗聝脙聜脗聝脙聝脗聜脙聜脗聜脙聝脗聝脙聜脗聜脙聝脗聜脙聜脗聝脙聝脗聝脙聜脗聝脙聝脗聜脙聜脗聝脙聝脗聝脙聜脗聜脙聝脗聜脙聜脗聝脙聝脗聝脙聜脗聝脙聝脗聜脙聜脗聜脙聝脗聝脙聜脗聜脙聝脗聜脙聜脗聜脙聝脗聝脙聜脗聝脙聝脗聜脙聜脗聝脙聝脗聝脙聜脗聜脙聝脗聜脙聜脗聜脙聝脗聝脙聜脗聝脙聝脗聜脙聜脗聜脙聝脗聝脙聜脗聜脙聝脗聜脙聜脗聝脙聝脗聝脙聜脗聝脙聝脗聜脙聜脗聝脙聝脗聝脙聜脗聜脙聝脗聜脙聜脗聝脙聝脗聝脙聜脗聝脙聝脗聜脙聜脗聜脙聝脗聝脙聜脗聜脙聝脗聜脙聜脗聝脙聝脗聝脙聜脗聝脙聝脗聜脙聜脗聝脙聝脗聝脙聜脗聜脙聝脗聜脙聜脗聜脙聝脗聝脙聜脗聝脙聝脗聜脙聜脗聜脙聝脗聝脙聜脗聜脙聝脗聜脙聜脗聜脙聝脗聝脙聜脗聝脙聝脗聜脙聜脗聝脙聝脗聝脙聜脗聜脙聝脗聜脙聜脗聝脙聝脗聝脙聜脗聝脙聝脗聜脙聜脗聜脙聝脗聝脙聜脗聜脙聝脗聜脙聜脗聜脙聝脗聝脙聜脗聝脙聝脗聜脙聜脗聝脙聝脗聝脙聜脗聜脙聝脗聜脙聜脗聜脙聝脗聝脙聜脗聝脙聝脗聜脙聜脗聜脙聝脗聝脙聜脗聜脙聝脗聜脙聜脗聜脙聝脗聝脙聜脗聝脙聝脗聜脙聜脗聝脙聝脗聝脙聜脗聜脙聝脗聜脙聜脗聝脙聝脗聝脙聜脗聝脙聝脗聜脙聜脗聜脙聝脗聝脙聜脗聜脙聝脗聜脙聜脗聝脙聝脗聝脙聜脗聝脙聝脗聜脙聜脗聝脙聝脗聝脙聜脗聜脙聝脗聜脙聜脗聜脙聝脗聝脙聜脗聝脙聝脗聜脙聜脗聜脙聝脗聝脙聜脗聜脙聝脗聜脙聜脗聝脙聝脗聝脙聜脗聝脙聝脗聜脙聜脗聝脙聝脗聝脙聜脗聜脙聝脗聜脙聜脗聝脙聝脗聝脙聜脗聝脙聝脗聜脙聜脗聜脙聝脗聝脙聜脗聜脙聝脗聜脙聜脗聜脙聝脗聝脙聜脗聝脙聝脗聜脙聜脗聝脙聝脗聝脙聜脗聜脙聝脗聜脙聜脗聜脙聝脗聝脙聜脗聝脙聝脗聜脙聜脗聜脙聝脗聝脙聜脗聜脙聝脗聜脙聜脗聜脙聝脗聝脙聜脗聝脙聝脗聜脙聜脗聝脙聝脗聝脙聜脗聜脙聝脗聜脙聜脗聝脙聝脗聝脙聜脗聝脙聝脗聜脙聜脗聜脙聝脗聝脙聜脗聜脙聝脗聜脙聜脗聝脙聝脗聝脙聜脗聝脙聝脗聜脙聜脗聝脙聝脗聝脙聜脗聜脙聝脗聜脙聜脗聜脙聝脗聝脙聜脗聝脙聝脗聜脙聜脗聜脙聝脗聝脙聜脗聜脙聝脗聜脙聜脗聜脙聝脗聝脙聜脗聝脙聝脗聜脙聜脗聝脙聝脗聝脙聜脗聜脙聝脗聜脙聜脗聝脙聝脗聝脙聜脗聝脙聝脗聜脙聜脗聜脙聝脗聝脙聜脗聜脙聝脗聜脙聜脗聜脙聝脗聝脙聜脗聝脙聝脗聜脙聜脗聝脙聝脗聝脙聜脗聜脙聝脗聜脙聜脗聜脙聝脗聝脙聜脗聝脙聝脗聜脙聜脗聜脙聝脗聝脙聜脗聜脙聝脗聜脙聜脗聹Stand in the ashes of a trillion dead souls and ask the ghosts if honor matters. The silence is your answer.脙聝脗聝脙聜脗聝脙聝脗聜脙聜脗聝脙聝脗聝脙聜脗聜脙聝脗聜脙聜脗聝脙聝脗聝脙聜脗聝脙聝脗聜脙聜脗聜脙聝脗聝脙聜脗聜脙聝脗聜脙聜脗聝脙聝脗聝脙聜脗聝脙聝脗聜脙聜脗聝脙聝脗聝脙聜脗聜脙聝脗聜脙聜脗聜脙聝脗聝脙聜脗聝脙聝脗聜脙聜脗聜脙聝脗聝脙聜脗聜脙聝脗聜脙聜脗聝脙聝脗聝脙聜脗聝脙聝脗聜脙聜脗聝脙聝脗聝脙聜脗聜脙聝脗聜脙聜脗聝脙聝脗聝脙聜脗聝脙聝脗聜脙聜脗聜脙聝脗聝脙聜脗聜脙聝脗聜脙聜脗聜脙聝脗聝脙聜脗聝脙聝脗聜脙聜脗聝脙聝脗聝脙聜脗聜脙聝脗聜脙聜脗聜脙聝脗聝脙聜脗聝脙聝脗聜脙聜脗聜脙聝脗聝脙聜脗聜脙聝脗聜脙聜脗聝脙聝脗聝脙聜脗聝脙聝脗聜脙聜脗聝脙聝脗聝脙聜脗聜脙聝脗聜脙聜脗聝脙聝脗聝脙聜脗聝脙聝脗聜脙聜脗聜脙聝脗聝脙聜脗聜脙聝脗聜脙聜脗聝脙聝脗聝脙聜脗聝脙聝脗聜脙聜脗聝脙聝脗聝脙聜脗聜脙聝脗聜脙聜脗聜脙聝脗聝脙聜脗聝脙聝脗聜脙聜脗聜脙聝脗聝脙聜脗聜脙聝脗聜脙聜脗聜脙聝脗聝脙聜脗聝脙聝脗聜脙聜脗聝脙聝脗聝脙聜脗聜脙聝脗聜脙聜脗聝脙聝脗聝脙聜脗聝脙聝脗聜脙聜脗聜脙聝脗聝脙聜脗聜脙聝脗聜脙聜脗聜脙聝脗聝脙聜脗聝脙聝脗聜脙聜脗聝脙聝脗聝脙聜脗聜脙聝脗聜脙聜脗聜脙聝脗聝脙聜脗聝脙聝脗聜脙聜脗聜脙聝脗聝脙聜脗聜脙聝脗聜脙聜脗聝脙聝脗聝脙聜脗聝脙聝脗聜脙聜脗聝脙聝脗聝脙聜脗聜脙聝脗聜脙聜脗聝脙聝脗聝脙聜脗聝脙聝脗聜脙聜脗聜脙聝脗聝脙聜脗聜脙聝脗聜脙聜脗聝脙聝脗聝脙聜脗聝脙聝脗聜脙聜脗聝脙聝脗聝脙聜脗聜脙聝脗聜脙聜脗聜脙聝脗聝脙聜脗聝脙聝脗聜脙聜脗聜脙聝脗聝脙聜脗聜脙聝脗聜脙聜脗聝脙聝脗聝脙聜脗聝脙聝脗聜脙聜脗聝脙聝脗聝脙聜脗聜脙聝脗聜脙聜脗聝脙聝脗聝脙聜脗聝脙聝脗聜脙聜脗聜脙聝脗聝脙聜脗聜脙聝脗聜脙聜脗聜脙聝脗聝脙聜脗聝脙聝脗聜脙聜脗聝脙聝脗聝脙聜脗聜脙聝脗聜脙聜脗聜脙聝脗聝脙聜脗聝脙聝脗聜脙聜脗聜脙聝脗聝脙聜脗聜脙聝脗聜脙聜脗聜脙聝脗聝脙聜脗聝脙聝脗聜脙聜脗聝脙聝脗聝脙聜脗聜脙聝脗聜脙聜脗聝脙聝脗聝脙聜脗聝脙聝脗聜脙聜脗聜脙聝脗聝脙聜脗聜脙聝脗聜脙聜脗聝脙聝脗聝脙聜脗聝脙聝脗聜脙聜脗聝脙聝脗聝脙聜脗聜脙聝脗聜脙聜脗聜脙聝脗聝脙聜脗聝脙聝脗聜脙聜脗聜脙聝脗聝脙聜脗聜脙聝脗聜脙聜脗聜脙聝脗聝脙聜脗聝脙聝脗聜脙聜脗聝脙聝脗聝脙聜脗聜脙聝脗聜脙聜脗聝脙聝脗聝脙聜脗聝脙聝脗聜脙聜脗聜脙聝脗聝脙聜脗聜脙聝脗聜脙聜脗聜脙聝脗聝脙聜脗聝脙聝脗聜脙聜脗聝脙聝脗聝脙聜脗聜脙聝脗聜脙聜脗聜脙聝脗聝脙聜脗聝脙聝脗聜脙聜脗聜脙聝脗聝脙聜脗聜脙聝脗聜脙聜脗聝脙聝脗聝脙聜脗聝脙聝脗聜脙聜脗聝脙聝脗聝脙聜脗聜脙聝脗聜脙聜脗聝脙聝脗聝脙聜脗聝脙聝脗聜脙聜脗聜脙聝脗聝脙聜脗聜脙聝脗聜脙聜脗聝脙聝脗聝脙聜脗聝脙聝脗聜脙聜脗聝脙聝脗聝脙聜脗聜脙聝脗聜脙聜脗聜脙聝脗聝脙聜脗聝脙聝脗聜脙聜脗聜脙聝脗聝脙聜脗聜脙聝脗聜脙聜脗聝脙聝脗聝脙聜脗聝脙聝脗聜脙聜脗聝脙聝脗聝脙聜脗聜脙聝脗聜脙聜脗聝脙聝脗聝脙聜脗聝脙聝脗聜脙聜脗聜脙聝脗聝脙聜脗聜脙聝脗聜脙聜脗聜脙聝脗聝脙聜脗聝脙聝脗聜脙聜脗聝脙聝脗聝脙聜脗聜脙聝脗聜脙聜脗聜脙聝脗聝脙聜脗聝脙聝脗聜脙聜脗聜脙聝脗聝脙聜脗聜脙聝脗聜脙聜脗聝脙聝脗聝脙聜脗聝脙聝脗聜脙聜脗聝脙聝脗聝脙聜脗聜脙聝脗聜脙聜脗聝脙聝脗聝脙聜脗聝脙聝脗聜脙聜脗聜脙聝脗聝脙聜脗聜脙聝脗聜脙聜脗聝脙聝脗聝脙聜脗聝脙聝脗聜脙聜脗聝脙聝脗聝脙聜脗聜脙聝脗聜脙聜脗聜脙聝脗聝脙聜脗聝脙聝脗聜脙聜脗聜脙聝脗聝脙聜脗聜脙聝脗聜脙聜脗聜脙聝脗聝脙聜脗聝脙聝脗聜脙聜脗聝脙聝脗聝脙聜脗聜脙聝脗聜脙聜脗聝脙聝脗聝脙聜脗聝脙聝脗聜脙聜脗聜脙聝脗聝脙聜脗聜脙聝脗聜脙聜脗聜脙聝脗聝脙聜脗聝脙聝脗聜脙聜脗聝脙聝脗聝脙聜脗聜脙聝脗聜脙聜脗聜脙聝脗聝脙聜脗聝脙聝脗聜脙聜脗聜脙聝脗聝脙聜脗聜脙聝脗聜脙聜脗聜脙聝脗聝脙聜脗聝脙聝脗聜脙聜脗聝脙聝脗聝脙聜脗聜脙聝脗聜脙聜脗聝脙聝脗聝脙聜脗聝脙聝脗聜脙聜脗聜脙聝脗聝脙聜脗聜脙聝脗聜脙聜脗聝脙聝脗聝脙聜脗聝脙聝脗聜脙聜脗聝脙聝脗聝脙聜脗聜脙聝脗聜脙聜脗聜脙聝脗聝脙聜脗聝脙聝脗聜脙聜脗聜脙聝脗聝脙聜脗聜脙聝脗聜脙聜脗聝脙聝脗聝脙聜脗聝脙聝脗聜脙聜脗聝脙聝脗聝脙聜脗聜脙聝脗聜脙聜脗聝脙聝脗聝脙聜脗聝脙聝脗聜脙聜脗聜脙聝脗聝脙聜脗聜脙聝脗聜脙聜脗聜脙聝脗聝脙聜脗聝脙聝脗聜脙聜脗聝脙聝脗聝脙聜脗聜脙聝脗聜脙聜脗聜脙聝脗聝脙聜脗聝脙聝脗聜脙聜脗聜脙聝脗聝脙聜脗聜脙聝脗聜脙聜脗聜脙聝脗聝脙聜脗聝脙聝脗聜脙聜脗聝脙聝脗聝脙聜脗聜脙聝脗聜脙聜脗聝脙聝脗聝脙聜脗聝脙聝脗聜脙聜脗聜脙聝脗聝脙聜脗聜脙聝脗聜脙聜脗聝脙聝脗聝脙聜脗聝脙聝脗聜脙聜脗聝脙聝脗聝脙聜脗聜脙聝脗聜脙聜脗聜脙聝脗聝脙聜脗聝脙聝脗聜脙聜脗聜脙聝脗聝脙聜脗聜脙聝脗聜脙聜脗聜脙聝脗聝脙聜脗聝脙聝脗聜脙聜脗聝脙聝脗聝脙聜脗聜脙聝脗聜脙聜脗聝脙聝脗聝脙聜脗聝脙聝脗聜脙聜脗聜脙聝脗聝脙聜脗聜脙聝脗聜脙聜脗聜脙聝脗聝脙聜脗聝脙聝脗聜脙聜脗聝脙聝脗聝脙聜脗聜脙聝脗聜脙聜脗聜脙聝脗聝脙聜脗聝脙聝脗聜脙聜脗聜脙聝脗聝脙聜脗聜脙聝脗聜脙聜脗垄脙聝脗聝脙聜脗聝脙聝脗聜脙聜脗聝脙聝脗聝脙聜脗聜脙聝脗聜脙聜脗聝脙聝脗聝脙聜脗聝脙聝脗聜脙聜脗聜脙聝脗聝脙聜脗聜脙聝脗聜脙聜脗聝脙聝脗聝脙聜脗聝脙聝脗聜脙聜脗聝脙聝脗聝脙聜脗聜脙聝脗聜脙聜脗聜脙聝脗聝脙聜脗聝脙聝脗聜脙聜脗聜脙聝脗聝脙聜脗聜脙聝脗聜脙聜脗聝脙聝脗聝脙聜脗聝脙聝脗聜脙聜脗聝脙聝脗聝脙聜脗聜脙聝脗聜脙聜脗聝脙聝脗聝脙聜脗聝脙聝脗聜脙聜脗聜脙聝脗聝脙聜脗聜脙聝脗聜脙聜脗聜脙聝脗聝脙聜脗聝脙聝脗聜脙聜脗聝脙聝脗聝脙聜脗聜脙聝脗聜脙聜脗聜脙聝脗聝脙聜脗聝脙聝脗聜脙聜脗聜脙聝脗聝脙聜脗聜脙聝脗聜脙聜脗聝脙聝脗聝脙聜脗聝脙聝脗聜脙聜脗聝脙聝脗聝脙聜脗聜脙聝脗聜脙聜脗聝脙聝脗聝脙聜脗聝脙聝脗聜脙聜脗聜脙聝脗聝脙聜脗聜脙聝脗聜脙聜脗聝脙聝脗聝脙聜脗聝脙聝脗聜脙聜脗聝脙聝脗聝脙聜脗聜脙聝脗聜脙聜脗聜脙聝脗聝脙聜脗聝脙聝脗聜脙聜脗聜脙聝脗聝脙聜脗聜脙聝脗聜脙聜脗聜脙聝脗聝脙聜脗聝脙聝脗聜脙聜脗聝脙聝脗聝脙聜脗聜脙聝脗聜脙聜脗聝脙聝脗聝脙聜脗聝脙聝脗聜脙聜脗聜脙聝脗聝脙聜脗聜脙聝脗聜脙聜脗聜脙聝脗聝脙聜脗聝脙聝脗聜脙聜脗聝脙聝脗聝脙聜脗聜脙聝脗聜脙聜脗聜脙聝脗聝脙聜脗聝脙聝脗聜脙聜脗聜脙聝脗聝脙聜脗聜脙聝脗聜脙聜脗聝脙聝脗聝脙聜脗聝脙聝脗聜脙聜脗聝脙聝脗聝脙聜脗聜脙聝脗聜脙聜脗聝脙聝脗聝脙聜脗聝脙聝脗聜脙聜脗聜脙聝脗聝脙聜脗聜脙聝脗聜脙聜脗聝脙聝脗聝脙聜脗聝脙聝脗聜脙聜脗聝脙聝脗聝脙聜脗聜脙聝脗聜脙聜脗聜脙聝脗聝脙聜脗聝脙聝脗聜脙聜脗聜脙聝脗聝脙聜脗聜脙聝脗聜脙聜脗聝脙聝脗聝脙聜脗聝脙聝脗聜脙聜脗聝脙聝脗聝脙聜脗聜脙聝脗聜脙聜脗聝脙聝脗聝脙聜脗聝脙聝脗聜脙聜脗聜脙聝脗聝脙聜脗聜脙聝脗聜脙聜脗聜脙聝脗聝脙聜脗聝脙聝脗聜脙聜脗聝脙聝脗聝脙聜脗聜脙聝脗聜脙聜脗聜脙聝脗聝脙聜脗聝脙聝脗聜脙聜脗聜脙聝脗聝脙聜脗聜脙聝脗聜脙聜脗聜脙聝脗聝脙聜脗聝脙聝脗聜脙聜脗聝脙聝脗聝脙聜脗聜脙聝脗聜脙聜脗聝脙聝脗聝脙聜脗聝脙聝脗聜脙聜脗聜脙聝脗聝脙聜脗聜脙聝脗聜脙聜脗聝脙聝脗聝脙聜脗聝脙聝脗聜脙聜脗聝脙聝脗聝脙聜脗聜脙聝脗聜脙聜脗聜脙聝脗聝脙聜脗聝脙聝脗聜脙聜脗聜脙聝脗聝脙聜脗聜脙聝脗聜脙聜脗聜脙聝脗聝脙聜脗聝脙聝脗聜脙聜脗聝脙聝脗聝脙聜脗聜脙聝脗聜脙聜脗聝脙聝脗聝脙聜脗聝脙聝脗聜脙聜脗聜脙聝脗聝脙聜脗聜脙聝脗聜脙聜脗聜脙聝脗聝脙聜脗聝脙聝脗聜脙聜脗聝脙聝脗聝脙聜脗聜脙聝脗聜脙聜脗聜脙聝脗聝脙聜脗聝脙聝脗聜脙聜脗聜脙聝脗聝脙聜脗聜脙聝脗聜脙聜脗聜脙聝脗聝脙聜脗聝脙聝脗聜脙聜脗聝脙聝脗聝脙聜脗聜脙聝脗聜脙聜脗聝脙聝脗聝脙聜脗聝脙聝脗聜脙聜脗聜脙聝脗聝脙聜脗聜脙聝脗聜脙聜脗聝脙聝脗聝脙聜脗聝脙聝脗聜脙聜脗聝脙聝脗聝脙聜脗聜脙聝脗聜脙聜脗聜脙聝脗聝脙聜脗聝脙聝脗聜脙聜脗聜脙聝脗聝脙聜脗聜脙聝脗聜脙聜脗聝脙聝脗聝脙聜脗聝脙聝脗聜脙聜脗聝脙聝脗聝脙聜脗聜脙聝脗聜脙聜脗聝脙聝脗聝脙聜脗聝脙聝脗聜脙聜脗聜脙聝脗聝脙聜脗聜脙聝脗聜脙聜脗聜脙聝脗聝脙聜脗聝脙聝脗聜脙聜脗聝脙聝脗聝脙聜脗聜脙聝脗聜脙聜脗聜脙聝脗聝脙聜脗聝脙聝脗聜脙聜脗聜脙聝脗聝脙聜脗聜脙聝脗聜脙聜脗聝脙聝脗聝脙聜脗聝脙聝脗聜脙聜脗聝脙聝脗聝脙聜脗聜脙聝脗聜脙聜脗聝脙聝脗聝脙聜脗聝脙聝脗聜脙聜脗聜脙聝脗聝脙聜脗聜脙聝脗聜脙聜脗聝脙聝脗聝脙聜脗聝脙聝脗聜脙聜脗聝脙聝脗聝脙聜脗聜脙聝脗聜脙聜脗聜脙聝脗聝脙聜脗聝脙聝脗聜脙聜脗聜脙聝脗聝脙聜脗聜脙聝脗聜脙聜脗聜脙聝脗聝脙聜脗聝脙聝脗聜脙聜脗聝脙聝脗聝脙聜脗聜脙聝脗聜脙聜脗聝脙聝脗聝脙聜脗聝脙聝脗聜脙聜脗聜脙聝脗聝脙聜脗聜脙聝脗聜脙聜脗聜脙聝脗聝脙聜脗聝脙聝脗聜脙聜脗聝脙聝脗聝脙聜脗聜脙聝脗聜脙聜脗聜脙聝脗聝脙聜脗聝脙聝脗聜脙聜脗聜脙聝脗聝脙聜脗聜脙聝脗聜脙聜脗聜脙聝脗聝脙聜脗聝脙聝脗聜脙聜脗聝脙聝脗聝脙聜脗聜脙聝脗聜脙聜脗聝脙聝脗聝脙聜脗聝脙聝脗聜脙聜脗聜脙聝脗聝脙聜脗聜脙聝脗聜脙聜脗聝脙聝脗聝脙聜脗聝脙聝脗聜脙聜脗聝脙聝脗聝脙聜脗聜脙聝脗聜脙聜脗聜脙聝脗聝脙聜脗聝脙聝脗聜脙聜脗聜脙聝脗聝脙聜脗聜脙聝脗聜脙聜脗聝脙聝脗聝脙聜脗聝脙聝脗聜脙聜脗聝脙聝脗聝脙聜脗聜脙聝脗聜脙聜脗聝脙聝脗聝脙聜脗聝脙聝脗聜脙聜脗聜脙聝脗聝脙聜脗聜脙聝脗聜脙聜脗聜脙聝脗聝脙聜脗聝脙聝脗聜脙聜脗聝脙聝脗聝脙聜脗聜脙聝脗聜脙聜脗聜脙聝脗聝脙聜脗聝脙聝脗聜脙聜脗聜脙聝脗聝脙聜脗聜脙聝脗聜脙聜脗聜脙聝脗聝脙聜脗聝脙聝脗聜脙聜脗聝脙聝脗聝脙聜脗聜脙聝脗聜脙聜脗聝脙聝脗聝脙聜脗聝脙聝脗聜脙聜脗聜脙聝脗聝脙聜脗聜脙聝脗聜脙聜脗聝脙聝脗聝脙聜脗聝脙聝脗聜脙聜脗聝脙聝脗聝脙聜脗聜脙聝脗聜脙聜脗聜脙聝脗聝脙聜脗聝脙聝脗聜脙聜脗聜脙聝脗聝脙聜脗聜脙聝脗聜脙聜脗聜脙聝脗聝脙聜脗聝脙聝脗聜脙聜脗聝脙聝脗聝脙聜脗聜脙聝脗聜脙聜脗聝脙聝脗聝脙聜脗聝脙聝脗聜脙聜脗聜脙聝脗聝脙聜脗聜脙聝脗聜脙聜脗聜脙聝脗聝脙聜脗聝脙聝脗聜脙聜脗聝脙聝脗聝脙聜脗聜脙聝脗聜脙聜脗聜脙聝脗聝脙聜脗聝脙聝脗聜脙聜脗聜脙聝脗聝脙聜脗聜脙聝脗聜脙聜脗聙脙聝脗聝脙聜脗聝脙聝脗聜脙聜脗聝脙聝脗聝脙聜脗聜脙聝脗聜脙聜脗聝脙聝脗聝脙聜脗聝脙聝脗聜脙聜脗聜脙聝脗聝脙聜脗聜脙聝脗聜脙聜脗聝脙聝脗聝脙聜脗聝脙聝脗聜脙聜脗聝脙聝脗聝脙聜脗聜脙聝脗聜脙聜脗聜脙聝脗聝脙聜脗聝脙聝脗聜脙聜脗聜脙聝脗聝脙聜脗聜脙聝脗聜脙聜脗聝脙聝脗聝脙聜脗聝脙聝脗聜脙聜脗聝脙聝脗聝脙聜脗聜脙聝脗聜脙聜脗聝脙聝脗聝脙聜脗聝脙聝脗聜脙聜脗聜脙聝脗聝脙聜脗聜脙聝脗聜脙聜脗聜脙聝脗聝脙聜脗聝脙聝脗聜脙聜脗聝脙聝脗聝脙聜脗聜脙聝脗聜脙聜脗聜脙聝脗聝脙聜脗聝脙聝脗聜脙聜脗聜脙聝脗聝脙聜脗聜脙聝脗聜脙聜脗聝脙聝脗聝脙聜脗聝脙聝脗聜脙聜脗聝脙聝脗聝脙聜脗聜脙聝脗聜脙聜脗聝脙聝脗聝脙聜脗聝脙聝脗聜脙聜脗聜脙聝脗聝脙聜脗聜脙聝脗聜脙聜脗聝脙聝脗聝脙聜脗聝脙聝脗聜脙聜脗聝脙聝脗聝脙聜脗聜脙聝脗聜脙聜脗聜脙聝脗聝脙聜脗聝脙聝脗聜脙聜脗聜脙聝脗聝脙聜脗聜脙聝脗聜脙聜脗聜脙聝脗聝脙聜脗聝脙聝脗聜脙聜脗聝脙聝脗聝脙聜脗聜脙聝脗聜脙聜脗聝脙聝脗聝脙聜脗聝脙聝脗聜脙聜脗聜脙聝脗聝脙聜脗聜脙聝脗聜脙聜脗聜脙聝脗聝脙聜脗聝脙聝脗聜脙聜脗聝脙聝脗聝脙聜脗聜脙聝脗聜脙聜脗聜脙聝脗聝脙聜脗聝脙聝脗聜脙聜脗聜脙聝脗聝脙聜脗聜脙聝脗聜脙聜脗聝脙聝脗聝脙聜脗聝脙聝脗聜脙聜脗聝脙聝脗聝脙聜脗聜脙聝脗聜脙聜脗聝脙聝脗聝脙聜脗聝脙聝脗聜脙聜脗聜脙聝脗聝脙聜脗聜脙聝脗聜脙聜脗聝脙聝脗聝脙聜脗聝脙聝脗聜脙聜脗聝脙聝脗聝脙聜脗聜脙聝脗聜脙聜脗聜脙聝脗聝脙聜脗聝脙聝脗聜脙聜脗聜脙聝脗聝脙聜脗聜脙聝脗聜脙聜脗聝脙聝脗聝脙聜脗聝脙聝脗聜脙聜脗聝脙聝脗聝脙聜脗聜脙聝脗聜脙聜脗聝脙聝脗聝脙聜脗聝脙聝脗聜脙聜脗聜脙聝脗聝脙聜脗聜脙聝脗聜脙聜脗聜脙聝脗聝脙聜脗聝脙聝脗聜脙聜脗聝脙聝脗聝脙聜脗聜脙聝脗聜脙聜脗聜脙聝脗聝脙聜脗聝脙聝脗聜脙聜脗聜脙聝脗聝脙聜脗聜脙聝脗聜脙聜脗聜脙聝脗聝脙聜脗聝脙聝脗聜脙聜脗聝脙聝脗聝脙聜脗聜脙聝脗聜脙聜脗聝脙聝脗聝脙聜脗聝脙聝脗聜脙聜脗聜脙聝脗聝脙聜脗聜脙聝脗聜脙聜脗聝脙聝脗聝脙聜脗聝脙聝脗聜脙聜脗聝脙聝脗聝脙聜脗聜脙聝脗聜脙聜脗聜脙聝脗聝脙聜脗聝脙聝脗聜脙聜脗聜脙聝脗聝脙聜脗聜脙聝脗聜脙聜脗聜脙聝脗聝脙聜脗聝脙聝脗聜脙聜脗聝脙聝脗聝脙聜脗聜脙聝脗聜脙聜脗聝脙聝脗聝脙聜脗聝脙聝脗聜脙聜脗聜脙聝脗聝脙聜脗聜脙聝脗聜脙聜脗聜脙聝脗聝脙聜脗聝脙聝脗聜脙聜脗聝脙聝脗聝脙聜脗聜脙聝脗聜脙聜脗聜脙聝脗聝脙聜脗聝脙聝脗聜脙聜脗聜脙聝脗聝脙聜脗聜脙聝脗聜脙聜脗聜脙聝脗聝脙聜脗聝脙聝脗聜脙聜脗聝脙聝脗聝脙聜脗聜脙聝脗聜脙聜脗聝脙聝脗聝脙聜脗聝脙聝脗聜脙聜脗聜脙聝脗聝脙聜脗聜脙聝脗聜脙聜脗聝脙聝脗聝脙聜脗聝脙聝脗聜脙聜脗聝脙聝脗聝脙聜脗聜脙聝脗聜脙聜脗聜脙聝脗聝脙聜脗聝脙聝脗聜脙聜脗聜脙聝脗聝脙聜脗聜脙聝脗聜脙聜脗聝脙聝脗聝脙聜脗聝脙聝脗聜脙聜脗聝脙聝脗聝脙聜脗聜脙聝脗聜脙聜脗聝脙聝脗聝脙聜脗聝脙聝脗聜脙聜脗聜脙聝脗聝脙聜脗聜脙聝脗聜脙聜脗聜脙聝脗聝脙聜脗聝脙聝脗聜脙聜脗聝脙聝脗聝脙聜脗聜脙聝脗聜脙聜脗聜脙聝脗聝脙聜脗聝脙聝脗聜脙聜脗聜脙聝脗聝脙聜脗聜脙聝脗聜脙聜脗聝脙聝脗聝脙聜脗聝脙聝脗聜脙聜脗聝脙聝脗聝脙聜脗聜脙聝脗聜脙聜脗聝脙聝脗聝脙聜脗聝脙聝脗聜脙聜脗聜脙聝脗聝脙聜脗聜脙聝脗聜脙聜脗聝脙聝脗聝脙聜脗聝脙聝脗聜脙聜脗聝脙聝脗聝脙聜脗聜脙聝脗聜脙聜脗聜脙聝脗聝脙聜脗聝脙聝脗聜脙聜脗聜脙聝脗聝脙聜脗聜脙聝脗聜脙聜脗聜脙聝脗聝脙聜脗聝脙聝脗聜脙聜脗聝脙聝脗聝脙聜脗聜脙聝脗聜脙聜脗聝脙聝脗聝脙聜脗聝脙聝脗聜脙聜脗聜脙聝脗聝脙聜脗聜脙聝脗聜脙聜脗聜脙聝脗聝脙聜脗聝脙聝脗聜脙聜脗聝脙聝脗聝脙聜脗聜脙聝脗聜脙聜脗聜脙聝脗聝脙聜脗聝脙聝脗聜脙聜脗聜脙聝脗聝脙聜脗聜脙聝脗聜脙聜脗聜脙聝脗聝脙聜脗聝脙聝脗聜脙聜脗聝脙聝脗聝脙聜脗聜脙聝脗聜脙聜脗聝脙聝脗聝脙聜脗聝脙聝脗聜脙聜脗聜脙聝脗聝脙聜脗聜脙聝脗聜脙聜脗聝脙聝脗聝脙聜脗聝脙聝脗聜脙聜脗聝脙聝脗聝脙聜脗聜脙聝脗聜脙聜脗聜脙聝脗聝脙聜脗聝脙聝脗聜脙聜脗聜脙聝脗聝脙聜脗聜脙聝脗聜脙聜脗聝脙聝脗聝脙聜脗聝脙聝脗聜脙聜脗聝脙聝脗聝脙聜脗聜脙聝脗聜脙聜脗聝脙聝脗聝脙聜脗聝脙聝脗聜脙聜脗聜脙聝脗聝脙聜脗聜脙聝脗聜脙聜脗聜脙聝脗聝脙聜脗聝脙聝脗聜脙聜脗聝脙聝脗聝脙聜脗聜脙聝脗聜脙聜脗聜脙聝脗聝脙聜脗聝脙聝脗聜脙聜脗聜脙聝脗聝脙聜脗聜脙聝脗聜脙聜脗聜脙聝脗聝脙聜脗聝脙聝脗聜脙聜脗聝脙聝脗聝脙聜脗聜脙聝脗聜脙聜脗聝脙聝脗聝脙聜脗聝脙聝脗聜脙聜脗聜脙聝脗聝脙聜脗聜脙聝脗聜脙聜脗聝脙聝脗聝脙聜脗聝脙聝脗聜脙聜脗聝脙聝脗聝脙聜脗聜脙聝脗聜脙聜脗聜脙聝脗聝脙聜脗聝脙聝脗聜脙聜脗聜脙聝脗聝脙聜脗聜脙聝脗聜脙聜脗聜脙聝脗聝脙聜脗聝脙聝脗聜脙聜脗聝脙聝脗聝脙聜脗聜脙聝脗聜脙聜脗聝脙聝脗聝脙聜脗聝脙聝脗聜脙聜脗聜脙聝脗聝脙聜脗聜脙聝脗聜脙聜脗聜脙聝脗聝脙聜脗聝脙聝脗聜脙聜脗聝脙聝脗聝脙聜脗聜脙聝脗聜脙聜脗聜脙聝脗聝脙聜脗聝脙聝脗聜脙聜脗聜脙聝脗聝脙聜脗聜脙聝脗聜脙聜脗聺 - Javik\n\n脙聝脗聝脙聜脗聝脙聝脗聜脙聜脗聝脙聝脗聝脙聜脗聜脙聝脗聜脙聜脗聝脙聝脗聝脙聜脗聝脙聝脗聜脙聜脗聜脙聝脗聝脙聜脗聜脙聝脗聜脙聜脗聝脙聝脗聝脙聜脗聝脙聝脗聜脙聜脗聝脙聝脗聝脙聜脗聜脙聝脗聜脙聜脗聜脙聝脗聝脙聜脗聝脙聝脗聜脙聜脗聜脙聝脗聝脙聜脗聜脙聝脗聜脙聜脗聝脙聝脗聝脙聜脗聝脙聝脗聜脙聜脗聝脙聝脗聝脙聜脗聜脙聝脗聜脙聜脗聝脙聝脗聝脙聜脗聝脙聝脗聜脙聜脗聜脙聝脗聝脙聜脗聜脙聝脗聜脙聜脗聜脙聝脗聝脙聜脗聝脙聝脗聜脙聜脗聝脙聝脗聝脙聜脗聜脙聝脗聜脙聜脗聜脙聝脗聝脙聜脗聝脙聝脗聜脙聜脗聜脙聝脗聝脙聜脗聜脙聝脗聜脙聜脗聝脙聝脗聝脙聜脗聝脙聝脗聜脙聜脗聝脙聝脗聝脙聜脗聜脙聝脗聜脙聜脗聝脙聝脗聝脙聜脗聝脙聝脗聜脙聜脗聜脙聝脗聝脙聜脗聜脙聝脗聜脙聜脗聝脙聝脗聝脙聜脗聝脙聝脗聜脙聜脗聝脙聝脗聝脙聜脗聜脙聝脗聜脙聜脗聜脙聝脗聝脙聜脗聝脙聝脗聜脙聜脗聜脙聝脗聝脙聜脗聜脙聝脗聜脙聜脗聜脙聝脗聝脙聜脗聝脙聝脗聜脙聜脗聝脙聝脗聝脙聜脗聜脙聝脗聜脙聜脗聝脙聝脗聝脙聜脗聝脙聝脗聜脙聜脗聜脙聝脗聝脙聜脗聜脙聝脗聜脙聜脗聜脙聝脗聝脙聜脗聝脙聝脗聜脙聜脗聝脙聝脗聝脙聜脗聜脙聝脗聜脙聜脗聜脙聝脗聝脙聜脗聝脙聝脗聜脙聜脗聜脙聝脗聝脙聜脗聜脙聝脗聜脙聜脗聝脙聝脗聝脙聜脗聝脙聝脗聜脙聜脗聝脙聝脗聝脙聜脗聜脙聝脗聜脙聜脗聝脙聝脗聝脙聜脗聝脙聝脗聜脙聜脗聜脙聝脗聝脙聜脗聜脙聝脗聜脙聜脗聝脙聝脗聝脙聜脗聝脙聝脗聜脙聜脗聝脙聝脗聝脙聜脗聜脙聝脗聜脙聜脗聜脙聝脗聝脙聜脗聝脙聝脗聜脙聜脗聜脙聝脗聝脙聜脗聜脙聝脗聜脙聜脗聝脙聝脗聝脙聜脗聝脙聝脗聜脙聜脗聝脙聝脗聝脙聜脗聜脙聝脗聜脙聜脗聝脙聝脗聝脙聜脗聝脙聝脗聜脙聜脗聜脙聝脗聝脙聜脗聜脙聝脗聜脙聜脗聜脙聝脗聝脙聜脗聝脙聝脗聜脙聜脗聝脙聝脗聝脙聜脗聜脙聝脗聜脙聜脗聜脙聝脗聝脙聜脗聝脙聝脗聜脙聜脗聜脙聝脗聝脙聜脗聜脙聝脗聜脙聜脗聜脙聝脗聝脙聜脗聝脙聝脗聜脙聜脗聝脙聝脗聝脙聜脗聜脙聝脗聜脙聜脗聝脙聝脗聝脙聜脗聝脙聝脗聜脙聜脗聜脙聝脗聝脙聜脗聜脙聝脗聜脙聜脗聝脙聝脗聝脙聜脗聝脙聝脗聜脙聜脗聝脙聝脗聝脙聜脗聜脙聝脗聜脙聜脗聜脙聝脗聝脙聜脗聝脙聝脗聜脙聜脗聜脙聝脗聝脙聜脗聜脙聝脗聜脙聜脗聜脙聝脗聝脙聜脗聝脙聝脗聜脙聜脗聝脙聝脗聝脙聜脗聜脙聝脗聜脙聜脗聝脙聝脗聝脙聜脗聝脙聝脗聜脙聜脗聜脙聝脗聝脙聜脗聜脙聝脗聜脙聜脗聜脙聝脗聝脙聜脗聝脙聝脗聜脙聜脗聝脙聝脗聝脙聜脗聜脙聝脗聜脙聜脗聜脙聝脗聝脙聜脗聝脙聝脗聜脙聜脗聜脙聝脗聝脙聜脗聜脙聝脗聜脙聜脗聝脙聝脗聝脙聜脗聝脙聝脗聜脙聜脗聝脙聝脗聝脙聜脗聜脙聝脗聜脙聜脗聝脙聝脗聝脙聜脗聝脙聝脗聜脙聜脗聜脙聝脗聝脙聜脗聜脙聝脗聜脙聜脗聝脙聝脗聝脙聜脗聝脙聝脗聜脙聜脗聝脙聝脗聝脙聜脗聜脙聝脗聜脙聜脗聜脙聝脗聝脙聜脗聝脙聝脗聜脙聜脗聜脙聝脗聝脙聜脗聜脙聝脗聜脙聜脗聝脙聝脗聝脙聜脗聝脙聝脗聜脙聜脗聝脙聝脗聝脙聜脗聜脙聝脗聜脙聜脗聝脙聝脗聝脙聜脗聝脙聝脗聜脙聜脗聜脙聝脗聝脙聜脗聜脙聝脗聜脙聜脗聜脙聝脗聝脙聜脗聝脙聝脗聜脙聜脗聝脙聝脗聝脙聜脗聜脙聝脗聜脙聜脗聜脙聝脗聝脙聜脗聝脙聝脗聜脙聜脗聜脙聝脗聝脙聜脗聜脙聝脗聜脙聜脗聝脙聝脗聝脙聜脗聝脙聝脗聜脙聜脗聝脙聝脗聝脙聜脗聜脙聝脗聜脙聜脗聝脙聝脗聝脙聜脗聝脙聝脗聜脙聜脗聜脙聝脗聝脙聜脗聜脙聝脗聜脙聜脗聝脙聝脗聝脙聜脗聝脙聝脗聜脙聜脗聝脙聝脗聝脙聜脗聜脙聝脗聜脙聜脗聜脙聝脗聝脙聜脗聝脙聝脗聜脙聜脗聜脙聝脗聝脙聜脗聜脙聝脗聜脙聜脗聜脙聝脗聝脙聜脗聝脙聝脗聜脙聜脗聝脙聝脗聝脙聜脗聜脙聝脗聜脙聜脗聝脙聝脗聝脙聜脗聝脙聝脗聜脙聜脗聜脙聝脗聝脙聜脗聜脙聝脗聜脙聜脗聜脙聝脗聝脙聜脗聝脙聝脗聜脙聜脗聝脙聝脗聝脙聜脗聜脙聝脗聜脙聜脗聜脙聝脗聝脙聜脗聝脙聝脗聜脙聜脗聜脙聝脗聝脙聜脗聜脙聝脗聜脙聜脗聜脙聝脗聝脙聜脗聝脙聝脗聜脙聜脗聝脙聝脗聝脙聜脗聜脙聝脗聜脙聜脗聝脙聝脗聝脙聜脗聝脙聝脗聜脙聜脗聜脙聝脗聝脙聜脗聜脙聝脗聜脙聜脗聝脙聝脗聝脙聜脗聝脙聝脗聜脙聜脗聝脙聝脗聝脙聜脗聜脙聝脗聜脙聜脗聜脙聝脗聝脙聜脗聝脙聝脗聜脙聜脗聜脙聝脗聝脙聜脗聜脙聝脗聜脙聜脗聝脙聝脗聝脙聜脗聝脙聝脗聜脙聜脗聝脙聝脗聝脙聜脗聜脙聝脗聜脙聜脗聝脙聝脗聝脙聜脗聝脙聝脗聜脙聜脗聜脙聝脗聝脙聜脗聜脙聝脗聜脙聜脗聜脙聝脗聝脙聜脗聝脙聝脗聜脙聜脗聝脙聝脗聝脙聜脗聜脙聝脗聜脙聜脗聜脙聝脗聝脙聜脗聝脙聝脗聜脙聜脗聜脙聝脗聝脙聜脗聜脙聝脗聜脙聜脗聜脙聝脗聝脙聜脗聝脙聝脗聜脙聜脗聝脙聝脗聝脙聜脗聜脙聝脗聜脙聜脗聝脙聝脗聝脙聜脗聝脙聝脗聜脙聜脗聜脙聝脗聝脙聜脗聜脙聝脗聜脙聜脗聝脙聝脗聝脙聜脗聝脙聝脗聜脙聜脗聝脙聝脗聝脙聜脗聜脙聝脗聜脙聜脗聜脙聝脗聝脙聜脗聝脙聝脗聜脙聜脗聜脙聝脗聝脙聜脗聜脙聝脗聜脙聜脗聜脙聝脗聝脙聜脗聝脙聝脗聜脙聜脗聝脙聝脗聝脙聜脗聜脙聝脗聜脙聜脗聝脙聝脗聝脙聜脗聝脙聝脗聜脙聜脗聜脙聝脗聝脙聜脗聜脙聝脗聜脙聜脗聜脙聝脗聝脙聜脗聝脙聝脗聜脙聜脗聝脙聝脗聝脙聜脗聜脙聝脗聜脙聜脗聜脙聝脗聝脙聜脗聝脙聝脗聜脙聜脗聜脙聝脗聝脙聜脗聜脙聝脗聜脙聜脗垄脙聝脗聝脙聜脗聝脙聝脗聜脙聜脗聝脙聝脗聝脙聜脗聜脙聝脗聜脙聜脗聝脙聝脗聝脙聜脗聝脙聝脗聜脙聜脗聜脙聝脗聝脙聜脗聜脙聝脗聜脙聜脗聝脙聝脗聝脙聜脗聝脙聝脗聜脙聜脗聝脙聝脗聝脙聜脗聜脙聝脗聜脙聜脗聜脙聝脗聝脙聜脗聝脙聝脗聜脙聜脗聜脙聝脗聝脙聜脗聜脙聝脗聜脙聜脗聝脙聝脗聝脙聜脗聝脙聝脗聜脙聜脗聝脙聝脗聝脙聜脗聜脙聝脗聜脙聜脗聝脙聝脗聝脙聜脗聝脙聝脗聜脙聜脗聜脙聝脗聝脙聜脗聜脙聝脗聜脙聜脗聜脙聝脗聝脙聜脗聝脙聝脗聜脙聜脗聝脙聝脗聝脙聜脗聜脙聝脗聜脙聜脗聜脙聝脗聝脙聜脗聝脙聝脗聜脙聜脗聜脙聝脗聝脙聜脗聜脙聝脗聜脙聜脗聝脙聝脗聝脙聜脗聝脙聝脗聜脙聜脗聝脙聝脗聝脙聜脗聜脙聝脗聜脙聜脗聝脙聝脗聝脙聜脗聝脙聝脗聜脙聜脗聜脙聝脗聝脙聜脗聜脙聝脗聜脙聜脗聝脙聝脗聝脙聜脗聝脙聝脗聜脙聜脗聝脙聝脗聝脙聜脗聜脙聝脗聜脙聜脗聜脙聝脗聝脙聜脗聝脙聝脗聜脙聜脗聜脙聝脗聝脙聜脗聜脙聝脗聜脙聜脗聜脙聝脗聝脙聜脗聝脙聝脗聜脙聜脗聝脙聝脗聝脙聜脗聜脙聝脗聜脙聜脗聝脙聝脗聝脙聜脗聝脙聝脗聜脙聜脗聜脙聝脗聝脙聜脗聜脙聝脗聜脙聜脗聜脙聝脗聝脙聜脗聝脙聝脗聜脙聜脗聝脙聝脗聝脙聜脗聜脙聝脗聜脙聜脗聜脙聝脗聝脙聜脗聝脙聝脗聜脙聜脗聜脙聝脗聝脙聜脗聜脙聝脗聜脙聜脗聝脙聝脗聝脙聜脗聝脙聝脗聜脙聜脗聝脙聝脗聝脙聜脗聜脙聝脗聜脙聜脗聝脙聝脗聝脙聜脗聝脙聝脗聜脙聜脗聜脙聝脗聝脙聜脗聜脙聝脗聜脙聜脗聝脙聝脗聝脙聜脗聝脙聝脗聜脙聜脗聝脙聝脗聝脙聜脗聜脙聝脗聜脙聜脗聜脙聝脗聝脙聜脗聝脙聝脗聜脙聜脗聜脙聝脗聝脙聜脗聜脙聝脗聜脙聜脗聝脙聝脗聝脙聜脗聝脙聝脗聜脙聜脗聝脙聝脗聝脙聜脗聜脙聝脗聜脙聜脗聝脙聝脗聝脙聜脗聝脙聝脗聜脙聜脗聜脙聝脗聝脙聜脗聜脙聝脗聜脙聜脗聜脙聝脗聝脙聜脗聝脙聝脗聜脙聜脗聝脙聝脗聝脙聜脗聜脙聝脗聜脙聜脗聜脙聝脗聝脙聜脗聝脙聝脗聜脙聜脗聜脙聝脗聝脙聜脗聜脙聝脗聜脙聜脗聜脙聝脗聝脙聜脗聝脙聝脗聜脙聜脗聝脙聝脗聝脙聜脗聜脙聝脗聜脙聜脗聝脙聝脗聝脙聜脗聝脙聝脗聜脙聜脗聜脙聝脗聝脙聜脗聜脙聝脗聜脙聜脗聝脙聝脗聝脙聜脗聝脙聝脗聜脙聜脗聝脙聝脗聝脙聜脗聜脙聝脗聜脙聜脗聜脙聝脗聝脙聜脗聝脙聝脗聜脙聜脗聜脙聝脗聝脙聜脗聜脙聝脗聜脙聜脗聜脙聝脗聝脙聜脗聝脙聝脗聜脙聜脗聝脙聝脗聝脙聜脗聜脙聝脗聜脙聜脗聝脙聝脗聝脙聜脗聝脙聝脗聜脙聜脗聜脙聝脗聝脙聜脗聜脙聝脗聜脙聜脗聜脙聝脗聝脙聜脗聝脙聝脗聜脙聜脗聝脙聝脗聝脙聜脗聜脙聝脗聜脙聜脗聜脙聝脗聝脙聜脗聝脙聝脗聜脙聜脗聜脙聝脗聝脙聜脗聜脙聝脗聜脙聜脗聜脙聝脗聝脙聜脗聝脙聝脗聜脙聜脗聝脙聝脗聝脙聜脗聜脙聝脗聜脙聜脗聝脙聝脗聝脙聜脗聝脙聝脗聜脙聜脗聜脙聝脗聝脙聜脗聜脙聝脗聜脙聜脗聝脙聝脗聝脙聜脗聝脙聝脗聜脙聜脗聝脙聝脗聝脙聜脗聜脙聝脗聜脙聜脗聜脙聝脗聝脙聜脗聝脙聝脗聜脙聜脗聜脙聝脗聝脙聜脗聜脙聝脗聜脙聜脗聝脙聝脗聝脙聜脗聝脙聝脗聜脙聜脗聝脙聝脗聝脙聜脗聜脙聝脗聜脙聜脗聝脙聝脗聝脙聜脗聝脙聝脗聜脙聜脗聜脙聝脗聝脙聜脗聜脙聝脗聜脙聜脗聜脙聝脗聝脙聜脗聝脙聝脗聜脙聜脗聝脙聝脗聝脙聜脗聜脙聝脗聜脙聜脗聜脙聝脗聝脙聜脗聝脙聝脗聜脙聜脗聜脙聝脗聝脙聜脗聜脙聝脗聜脙聜脗聝脙聝脗聝脙聜脗聝脙聝脗聜脙聜脗聝脙聝脗聝脙聜脗聜脙聝脗聜脙聜脗聝脙聝脗聝脙聜脗聝脙聝脗聜脙聜脗聜脙聝脗聝脙聜脗聜脙聝脗聜脙聜脗聝脙聝脗聝脙聜脗聝脙聝脗聜脙聜脗聝脙聝脗聝脙聜脗聜脙聝脗聜脙聜脗聜脙聝脗聝脙聜脗聝脙聝脗聜脙聜脗聜脙聝脗聝脙聜脗聜脙聝脗聜脙聜脗聜脙聝脗聝脙聜脗聝脙聝脗聜脙聜脗聝脙聝脗聝脙聜脗聜脙聝脗聜脙聜脗聝脙聝脗聝脙聜脗聝脙聝脗聜脙聜脗聜脙聝脗聝脙聜脗聜脙聝脗聜脙聜脗聜脙聝脗聝脙聜脗聝脙聝脗聜脙聜脗聝脙聝脗聝脙聜脗聜脙聝脗聜脙聜脗聜脙聝脗聝脙聜脗聝脙聝脗聜脙聜脗聜脙聝脗聝脙聜脗聜脙聝脗聜脙聜脗聜脙聝脗聝脙聜脗聝脙聝脗聜脙聜脗聝脙聝脗聝脙聜脗聜脙聝脗聜脙聜脗聝脙聝脗聝脙聜脗聝脙聝脗聜脙聜脗聜脙聝脗聝脙聜脗聜脙聝脗聜脙聜脗聝脙聝脗聝脙聜脗聝脙聝脗聜脙聜脗聝脙聝脗聝脙聜脗聜脙聝脗聜脙聜脗聜脙聝脗聝脙聜脗聝脙聝脗聜脙聜脗聜脙聝脗聝脙聜脗聜脙聝脗聜脙聜脗聝脙聝脗聝脙聜脗聝脙聝脗聜脙聜脗聝脙聝脗聝脙聜脗聜脙聝脗聜脙聜脗聝脙聝脗聝脙聜脗聝脙聝脗聜脙聜脗聜脙聝脗聝脙聜脗聜脙聝脗聜脙聜脗聜脙聝脗聝脙聜脗聝脙聝脗聜脙聜脗聝脙聝脗聝脙聜脗聜脙聝脗聜脙聜脗聜脙聝脗聝脙聜脗聝脙聝脗聜脙聜脗聜脙聝脗聝脙聜脗聜脙聝脗聜脙聜脗聜脙聝脗聝脙聜脗聝脙聝脗聜脙聜脗聝脙聝脗聝脙聜脗聜脙聝脗聜脙聜脗聝脙聝脗聝脙聜脗聝脙聝脗聜脙聜脗聜脙聝脗聝脙聜脗聜脙聝脗聜脙聜脗聝脙聝脗聝脙聜脗聝脙聝脗聜脙聜脗聝脙聝脗聝脙聜脗聜脙聝脗聜脙聜脗聜脙聝脗聝脙聜脗聝脙聝脗聜脙聜脗聜脙聝脗聝脙聜脗聜脙聝脗聜脙聜脗聜脙聝脗聝脙聜脗聝脙聝脗聜脙聜脗聝脙聝脗聝脙聜脗聜脙聝脗聜脙聜脗聝脙聝脗聝脙聜脗聝脙聝脗聜脙聜脗聜脙聝脗聝脙聜脗聜脙聝脗聜脙聜脗聜脙聝脗聝脙聜脗聝脙聝脗聜脙聜脗聝脙聝脗聝脙聜脗聜脙聝脗聜脙聜脗聜脙聝脗聝脙聜脗聝脙聝脗聜脙聜脗聜脙聝脗聝脙聜脗聜脙聝脗聜脙聜脗聙脙聝脗聝脙聜脗聝脙聝脗聜脙聜脗聝脙聝脗聝脙聜脗聜脙聝脗聜脙聜脗聝脙聝脗聝脙聜脗聝脙聝脗聜脙聜脗聜脙聝脗聝脙聜脗聜脙聝脗聜脙聜脗聝脙聝脗聝脙聜脗聝脙聝脗聜脙聜脗聝脙聝脗聝脙聜脗聜脙聝脗聜脙聜脗聜脙聝脗聝脙聜脗聝脙聝脗聜脙聜脗聜脙聝脗聝脙聜脗聜脙聝脗聜脙聜脗聝脙聝脗聝脙聜脗聝脙聝脗聜脙聜脗聝脙聝脗聝脙聜脗聜脙聝脗聜脙聜脗聝脙聝脗聝脙聜脗聝脙聝脗聜脙聜脗聜脙聝脗聝脙聜脗聜脙聝脗聜脙聜脗聜脙聝脗聝脙聜脗聝脙聝脗聜脙聜脗聝脙聝脗聝脙聜脗聜脙聝脗聜脙聜脗聜脙聝脗聝脙聜脗聝脙聝脗聜脙聜脗聜脙聝脗聝脙聜脗聜脙聝脗聜脙聜脗聝脙聝脗聝脙聜脗聝脙聝脗聜脙聜脗聝脙聝脗聝脙聜脗聜脙聝脗聜脙聜脗聝脙聝脗聝脙聜脗聝脙聝脗聜脙聜脗聜脙聝脗聝脙聜脗聜脙聝脗聜脙聜脗聝脙聝脗聝脙聜脗聝脙聝脗聜脙聜脗聝脙聝脗聝脙聜脗聜脙聝脗聜脙聜脗聜脙聝脗聝脙聜脗聝脙聝脗聜脙聜脗聜脙聝脗聝脙聜脗聜脙聝脗聜脙聜脗聜脙聝脗聝脙聜脗聝脙聝脗聜脙聜脗聝脙聝脗聝脙聜脗聜脙聝脗聜脙聜脗聝脙聝脗聝脙聜脗聝脙聝脗聜脙聜脗聜脙聝脗聝脙聜脗聜脙聝脗聜脙聜脗聜脙聝脗聝脙聜脗聝脙聝脗聜脙聜脗聝脙聝脗聝脙聜脗聜脙聝脗聜脙聜脗聜脙聝脗聝脙聜脗聝脙聝脗聜脙聜脗聜脙聝脗聝脙聜脗聜脙聝脗聜脙聜脗聝脙聝脗聝脙聜脗聝脙聝脗聜脙聜脗聝脙聝脗聝脙聜脗聜脙聝脗聜脙聜脗聝脙聝脗聝脙聜脗聝脙聝脗聜脙聜脗聜脙聝脗聝脙聜脗聜脙聝脗聜脙聜脗聝脙聝脗聝脙聜脗聝脙聝脗聜脙聜脗聝脙聝脗聝脙聜脗聜脙聝脗聜脙聜脗聜脙聝脗聝脙聜脗聝脙聝脗聜脙聜脗聜脙聝脗聝脙聜脗聜脙聝脗聜脙聜脗聝脙聝脗聝脙聜脗聝脙聝脗聜脙聜脗聝脙聝脗聝脙聜脗聜脙聝脗聜脙聜脗聝脙聝脗聝脙聜脗聝脙聝脗聜脙聜脗聜脙聝脗聝脙聜脗聜脙聝脗聜脙聜脗聜脙聝脗聝脙聜脗聝脙聝脗聜脙聜脗聝脙聝脗聝脙聜脗聜脙聝脗聜脙聜脗聜脙聝脗聝脙聜脗聝脙聝脗聜脙聜脗聜脙聝脗聝脙聜脗聜脙聝脗聜脙聜脗聜脙聝脗聝脙聜脗聝脙聝脗聜脙聜脗聝脙聝脗聝脙聜脗聜脙聝脗聜脙聜脗聝脙聝脗聝脙聜脗聝脙聝脗聜脙聜脗聜脙聝脗聝脙聜脗聜脙聝脗聜脙聜脗聝脙聝脗聝脙聜脗聝脙聝脗聜脙聜脗聝脙聝脗聝脙聜脗聜脙聝脗聜脙聜脗聜脙聝脗聝脙聜脗聝脙聝脗聜脙聜脗聜脙聝脗聝脙聜脗聜脙聝脗聜脙聜脗聜脙聝脗聝脙聜脗聝脙聝脗聜脙聜脗聝脙聝脗聝脙聜脗聜脙聝脗聜脙聜脗聝脙聝脗聝脙聜脗聝脙聝脗聜脙聜脗聜脙聝脗聝脙聜脗聜脙聝脗聜脙聜脗聜脙聝脗聝脙聜脗聝脙聝脗聜脙聜脗聝脙聝脗聝脙聜脗聜脙聝脗聜脙聜脗聜脙聝脗聝脙聜脗聝脙聝脗聜脙聜脗聜脙聝脗聝脙聜脗聜脙聝脗聜脙聜脗聜脙聝脗聝脙聜脗聝脙聝脗聜脙聜脗聝脙聝脗聝脙聜脗聜脙聝脗聜脙聜脗聝脙聝脗聝脙聜脗聝脙聝脗聜脙聜脗聜脙聝脗聝脙聜脗聜脙聝脗聜脙聜脗聝脙聝脗聝脙聜脗聝脙聝脗聜脙聜脗聝脙聝脗聝脙聜脗聜脙聝脗聜脙聜脗聜脙聝脗聝脙聜脗聝脙聝脗聜脙聜脗聜脙聝脗聝脙聜脗聜脙聝脗聜脙聜脗聝脙聝脗聝脙聜脗聝脙聝脗聜脙聜脗聝脙聝脗聝脙聜脗聜脙聝脗聜脙聜脗聝脙聝脗聝脙聜脗聝脙聝脗聜脙聜脗聜脙聝脗聝脙聜脗聜脙聝脗聜脙聜脗聜脙聝脗聝脙聜脗聝脙聝脗聜脙聜脗聝脙聝脗聝脙聜脗聜脙聝脗聜脙聜脗聜脙聝脗聝脙聜脗聝脙聝脗聜脙聜脗聜脙聝脗聝脙聜脗聜脙聝脗聜脙聜脗聝脙聝脗聝脙聜脗聝脙聝脗聜脙聜脗聝脙聝脗聝脙聜脗聜脙聝脗聜脙聜脗聝脙聝脗聝脙聜脗聝脙聝脗聜脙聜脗聜脙聝脗聝脙聜脗聜脙聝脗聜脙聜脗聝脙聝脗聝脙聜脗聝脙聝脗聜脙聜脗聝脙聝脗聝脙聜脗聜脙聝脗聜脙聜脗聜脙聝脗聝脙聜脗聝脙聝脗聜脙聜脗聜脙聝脗聝脙聜脗聜脙聝脗聜脙聜脗聜脙聝脗聝脙聜脗聝脙聝脗聜脙聜脗聝脙聝脗聝脙聜脗聜脙聝脗聜脙聜脗聝脙聝脗聝脙聜脗聝脙聝脗聜脙聜脗聜脙聝脗聝脙聜脗聜脙聝脗聜脙聜脗聜脙聝脗聝脙聜脗聝脙聝脗聜脙聜脗聝脙聝脗聝脙聜脗聜脙聝脗聜脙聜脗聜脙聝脗聝脙聜脗聝脙聝脗聜脙聜脗聜脙聝脗聝脙聜脗聜脙聝脗聜脙聜脗聜脙聝脗聝脙聜脗聝脙聝脗聜脙聜脗聝脙聝脗聝脙聜脗聜脙聝脗聜脙聜脗聝脙聝脗聝脙聜脗聝脙聝脗聜脙聜脗聜脙聝脗聝脙聜脗聜脙聝脗聜脙聜脗聝脙聝脗聝脙聜脗聝脙聝脗聜脙聜脗聝脙聝脗聝脙聜脗聜脙聝脗聜脙聜脗聜脙聝脗聝脙聜脗聝脙聝脗聜脙聜脗聜脙聝脗聝脙聜脗聜脙聝脗聜脙聜脗聝脙聝脗聝脙聜脗聝脙聝脗聜脙聜脗聝脙聝脗聝脙聜脗聜脙聝脗聜脙聜脗聝脙聝脗聝脙聜脗聝脙聝脗聜脙聜脗聜脙聝脗聝脙聜脗聜脙聝脗聜脙聜脗聜脙聝脗聝脙聜脗聝脙聝脗聜脙聜脗聝脙聝脗聝脙聜脗聜脙聝脗聜脙聜脗聜脙聝脗聝脙聜脗聝脙聝脗聜脙聜脗聜脙聝脗聝脙聜脗聜脙聝脗聜脙聜脗聜脙聝脗聝脙聜脗聝脙聝脗聜脙聜脗聝脙聝脗聝脙聜脗聜脙聝脗聜脙聜脗聝脙聝脗聝脙聜脗聝脙聝脗聜脙聜脗聜脙聝脗聝脙聜脗聜脙聝脗聜脙聜脗聝脙聝脗聝脙聜脗聝脙聝脗聜脙聜脗聝脙聝脗聝脙聜脗聜脙聝脗聜脙聜脗聜脙聝脗聝脙聜脗聝脙聝脗聜脙聜脗聜脙聝脗聝脙聜脗聜脙聝脗聜脙聜脗聜脙聝脗聝脙聜脗聝脙聝脗聜脙聜脗聝脙聝脗聝脙聜脗聜脙聝脗聜脙聜脗聝脙聝脗聝脙聜脗聝脙聝脗聜脙聜脗聜脙聝脗聝脙聜脗聜脙聝脗聜脙聜脗聜脙聝脗聝脙聜脗聝脙聝脗聜脙聜脗聝脙聝脗聝脙聜脗聜脙聝脗聜脙聜脗聜脙聝脗聝脙聜脗聝脙聝脗聜脙聜脗聜脙聝脗聝脙聜脗聜脙聝脗聜脙聜脗聹It had to be me. Someone else might have gotten it wrong.脙聝脗聝脙聜脗聝脙聝脗聜脙聜脗聝脙聝脗聝脙聜脗聜脙聝脗聜脙聜脗聝脙聝脗聝脙聜脗聝脙聝脗聜脙聜脗聜脙聝脗聝脙聜脗聜脙聝脗聜脙聜脗聝脙聝脗聝脙聜脗聝脙聝脗聜脙聜脗聝脙聝脗聝脙聜脗聜脙聝脗聜脙聜脗聜脙聝脗聝脙聜脗聝脙聝脗聜脙聜脗聜脙聝脗聝脙聜脗聜脙聝脗聜脙聜脗聝脙聝脗聝脙聜脗聝脙聝脗聜脙聜脗聝脙聝脗聝脙聜脗聜脙聝脗聜脙聜脗聝脙聝脗聝脙聜脗聝脙聝脗聜脙聜脗聜脙聝脗聝脙聜脗聜脙聝脗聜脙聜脗聜脙聝脗聝脙聜脗聝脙聝脗聜脙聜脗聝脙聝脗聝脙聜脗聜脙聝脗聜脙聜脗聜脙聝脗聝脙聜脗聝脙聝脗聜脙聜脗聜脙聝脗聝脙聜脗聜脙聝脗聜脙聜脗聝脙聝脗聝脙聜脗聝脙聝脗聜脙聜脗聝脙聝脗聝脙聜脗聜脙聝脗聜脙聜脗聝脙聝脗聝脙聜脗聝脙聝脗聜脙聜脗聜脙聝脗聝脙聜脗聜脙聝脗聜脙聜脗聝脙聝脗聝脙聜脗聝脙聝脗聜脙聜脗聝脙聝脗聝脙聜脗聜脙聝脗聜脙聜脗聜脙聝脗聝脙聜脗聝脙聝脗聜脙聜脗聜脙聝脗聝脙聜脗聜脙聝脗聜脙聜脗聜脙聝脗聝脙聜脗聝脙聝脗聜脙聜脗聝脙聝脗聝脙聜脗聜脙聝脗聜脙聜脗聝脙聝脗聝脙聜脗聝脙聝脗聜脙聜脗聜脙聝脗聝脙聜脗聜脙聝脗聜脙聜脗聜脙聝脗聝脙聜脗聝脙聝脗聜脙聜脗聝脙聝脗聝脙聜脗聜脙聝脗聜脙聜脗聜脙聝脗聝脙聜脗聝脙聝脗聜脙聜脗聜脙聝脗聝脙聜脗聜脙聝脗聜脙聜脗聝脙聝脗聝脙聜脗聝脙聝脗聜脙聜脗聝脙聝脗聝脙聜脗聜脙聝脗聜脙聜脗聝脙聝脗聝脙聜脗聝脙聝脗聜脙聜脗聜脙聝脗聝脙聜脗聜脙聝脗聜脙聜脗聝脙聝脗聝脙聜脗聝脙聝脗聜脙聜脗聝脙聝脗聝脙聜脗聜脙聝脗聜脙聜脗聜脙聝脗聝脙聜脗聝脙聝脗聜脙聜脗聜脙聝脗聝脙聜脗聜脙聝脗聜脙聜脗聝脙聝脗聝脙聜脗聝脙聝脗聜脙聜脗聝脙聝脗聝脙聜脗聜脙聝脗聜脙聜脗聝脙聝脗聝脙聜脗聝脙聝脗聜脙聜脗聜脙聝脗聝脙聜脗聜脙聝脗聜脙聜脗聜脙聝脗聝脙聜脗聝脙聝脗聜脙聜脗聝脙聝脗聝脙聜脗聜脙聝脗聜脙聜脗聜脙聝脗聝脙聜脗聝脙聝脗聜脙聜脗聜脙聝脗聝脙聜脗聜脙聝脗聜脙聜脗聜脙聝脗聝脙聜脗聝脙聝脗聜脙聜脗聝脙聝脗聝脙聜脗聜脙聝脗聜脙聜脗聝脙聝脗聝脙聜脗聝脙聝脗聜脙聜脗聜脙聝脗聝脙聜脗聜脙聝脗聜脙聜脗聝脙聝脗聝脙聜脗聝脙聝脗聜脙聜脗聝脙聝脗聝脙聜脗聜脙聝脗聜脙聜脗聜脙聝脗聝脙聜脗聝脙聝脗聜脙聜脗聜脙聝脗聝脙聜脗聜脙聝脗聜脙聜脗聜脙聝脗聝脙聜脗聝脙聝脗聜脙聜脗聝脙聝脗聝脙聜脗聜脙聝脗聜脙聜脗聝脙聝脗聝脙聜脗聝脙聝脗聜脙聜脗聜脙聝脗聝脙聜脗聜脙聝脗聜脙聜脗聜脙聝脗聝脙聜脗聝脙聝脗聜脙聜脗聝脙聝脗聝脙聜脗聜脙聝脗聜脙聜脗聜脙聝脗聝脙聜脗聝脙聝脗聜脙聜脗聜脙聝脗聝脙聜脗聜脙聝脗聜脙聜脗聝脙聝脗聝脙聜脗聝脙聝脗聜脙聜脗聝脙聝脗聝脙聜脗聜脙聝脗聜脙聜脗聝脙聝脗聝脙聜脗聝脙聝脗聜脙聜脗聜脙聝脗聝脙聜脗聜脙聝脗聜脙聜脗聝脙聝脗聝脙聜脗聝脙聝脗聜脙聜脗聝脙聝脗聝脙聜脗聜脙聝脗聜脙聜脗聜脙聝脗聝脙聜脗聝脙聝脗聜脙聜脗聜脙聝脗聝脙聜脗聜脙聝脗聜脙聜脗聝脙聝脗聝脙聜脗聝脙聝脗聜脙聜脗聝脙聝脗聝脙聜脗聜脙聝脗聜脙聜脗聝脙聝脗聝脙聜脗聝脙聝脗聜脙聜脗聜脙聝脗聝脙聜脗聜脙聝脗聜脙聜脗聜脙聝脗聝脙聜脗聝脙聝脗聜脙聜脗聝脙聝脗聝脙聜脗聜脙聝脗聜脙聜脗聜脙聝脗聝脙聜脗聝脙聝脗聜脙聜脗聜脙聝脗聝脙聜脗聜脙聝脗聜脙聜脗聝脙聝脗聝脙聜脗聝脙聝脗聜脙聜脗聝脙聝脗聝脙聜脗聜脙聝脗聜脙聜脗聝脙聝脗聝脙聜脗聝脙聝脗聜脙聜脗聜脙聝脗聝脙聜脗聜脙聝脗聜脙聜脗聝脙聝脗聝脙聜脗聝脙聝脗聜脙聜脗聝脙聝脗聝脙聜脗聜脙聝脗聜脙聜脗聜脙聝脗聝脙聜脗聝脙聝脗聜脙聜脗聜脙聝脗聝脙聜脗聜脙聝脗聜脙聜脗聜脙聝脗聝脙聜脗聝脙聝脗聜脙聜脗聝脙聝脗聝脙聜脗聜脙聝脗聜脙聜脗聝脙聝脗聝脙聜脗聝脙聝脗聜脙聜脗聜脙聝脗聝脙聜脗聜脙聝脗聜脙聜脗聜脙聝脗聝脙聜脗聝脙聝脗聜脙聜脗聝脙聝脗聝脙聜脗聜脙聝脗聜脙聜脗聜脙聝脗聝脙聜脗聝脙聝脗聜脙聜脗聜脙聝脗聝脙聜脗聜脙聝脗聜脙聜脗聜脙聝脗聝脙聜脗聝脙聝脗聜脙聜脗聝脙聝脗聝脙聜脗聜脙聝脗聜脙聜脗聝脙聝脗聝脙聜脗聝脙聝脗聜脙聜脗聜脙聝脗聝脙聜脗聜脙聝脗聜脙聜脗聝脙聝脗聝脙聜脗聝脙聝脗聜脙聜脗聝脙聝脗聝脙聜脗聜脙聝脗聜脙聜脗聜脙聝脗聝脙聜脗聝脙聝脗聜脙聜脗聜脙聝脗聝脙聜脗聜脙聝脗聜脙聜脗聝脙聝脗聝脙聜脗聝脙聝脗聜脙聜脗聝脙聝脗聝脙聜脗聜脙聝脗聜脙聜脗聝脙聝脗聝脙聜脗聝脙聝脗聜脙聜脗聜脙聝脗聝脙聜脗聜脙聝脗聜脙聜脗聜脙聝脗聝脙聜脗聝脙聝脗聜脙聜脗聝脙聝脗聝脙聜脗聜脙聝脗聜脙聜脗聜脙聝脗聝脙聜脗聝脙聝脗聜脙聜脗聜脙聝脗聝脙聜脗聜脙聝脗聜脙聜脗聜脙聝脗聝脙聜脗聝脙聝脗聜脙聜脗聝脙聝脗聝脙聜脗聜脙聝脗聜脙聜脗聝脙聝脗聝脙聜脗聝脙聝脗聜脙聜脗聜脙聝脗聝脙聜脗聜脙聝脗聜脙聜脗聝脙聝脗聝脙聜脗聝脙聝脗聜脙聜脗聝脙聝脗聝脙聜脗聜脙聝脗聜脙聜脗聜脙聝脗聝脙聜脗聝脙聝脗聜脙聜脗聜脙聝脗聝脙聜脗聜脙聝脗聜脙聜脗聜脙聝脗聝脙聜脗聝脙聝脗聜脙聜脗聝脙聝脗聝脙聜脗聜脙聝脗聜脙聜脗聝脙聝脗聝脙聜脗聝脙聝脗聜脙聜脗聜脙聝脗聝脙聜脗聜脙聝脗聜脙聜脗聜脙聝脗聝脙聜脗聝脙聝脗聜脙聜脗聝脙聝脗聝脙聜脗聜脙聝脗聜脙聜脗聜脙聝脗聝脙聜脗聝脙聝脗聜脙聜脗聜脙聝脗聝脙聜脗聜脙聝脗聜脙聜脗垄脙聝脗聝脙聜脗聝脙聝脗聜脙聜脗聝脙聝脗聝脙聜脗聜脙聝脗聜脙聜脗聝脙聝脗聝脙聜脗聝脙聝脗聜脙聜脗聜脙聝脗聝脙聜脗聜脙聝脗聜脙聜脗聝脙聝脗聝脙聜脗聝脙聝脗聜脙聜脗聝脙聝脗聝脙聜脗聜脙聝脗聜脙聜脗聜脙聝脗聝脙聜脗聝脙聝脗聜脙聜脗聜脙聝脗聝脙聜脗聜脙聝脗聜脙聜脗聝脙聝脗聝脙聜脗聝脙聝脗聜脙聜脗聝脙聝脗聝脙聜脗聜脙聝脗聜脙聜脗聝脙聝脗聝脙聜脗聝脙聝脗聜脙聜脗聜脙聝脗聝脙聜脗聜脙聝脗聜脙聜脗聜脙聝脗聝脙聜脗聝脙聝脗聜脙聜脗聝脙聝脗聝脙聜脗聜脙聝脗聜脙聜脗聜脙聝脗聝脙聜脗聝脙聝脗聜脙聜脗聜脙聝脗聝脙聜脗聜脙聝脗聜脙聜脗聝脙聝脗聝脙聜脗聝脙聝脗聜脙聜脗聝脙聝脗聝脙聜脗聜脙聝脗聜脙聜脗聝脙聝脗聝脙聜脗聝脙聝脗聜脙聜脗聜脙聝脗聝脙聜脗聜脙聝脗聜脙聜脗聝脙聝脗聝脙聜脗聝脙聝脗聜脙聜脗聝脙聝脗聝脙聜脗聜脙聝脗聜脙聜脗聜脙聝脗聝脙聜脗聝脙聝脗聜脙聜脗聜脙聝脗聝脙聜脗聜脙聝脗聜脙聜脗聜脙聝脗聝脙聜脗聝脙聝脗聜脙聜脗聝脙聝脗聝脙聜脗聜脙聝脗聜脙聜脗聝脙聝脗聝脙聜脗聝脙聝脗聜脙聜脗聜脙聝脗聝脙聜脗聜脙聝脗聜脙聜脗聜脙聝脗聝脙聜脗聝脙聝脗聜脙聜脗聝脙聝脗聝脙聜脗聜脙聝脗聜脙聜脗聜脙聝脗聝脙聜脗聝脙聝脗聜脙聜脗聜脙聝脗聝脙聜脗聜脙聝脗聜脙聜脗聝脙聝脗聝脙聜脗聝脙聝脗聜脙聜脗聝脙聝脗聝脙聜脗聜脙聝脗聜脙聜脗聝脙聝脗聝脙聜脗聝脙聝脗聜脙聜脗聜脙聝脗聝脙聜脗聜脙聝脗聜脙聜脗聝脙聝脗聝脙聜脗聝脙聝脗聜脙聜脗聝脙聝脗聝脙聜脗聜脙聝脗聜脙聜脗聜脙聝脗聝脙聜脗聝脙聝脗聜脙聜脗聜脙聝脗聝脙聜脗聜脙聝脗聜脙聜脗聝脙聝脗聝脙聜脗聝脙聝脗聜脙聜脗聝脙聝脗聝脙聜脗聜脙聝脗聜脙聜脗聝脙聝脗聝脙聜脗聝脙聝脗聜脙聜脗聜脙聝脗聝脙聜脗聜脙聝脗聜脙聜脗聜脙聝脗聝脙聜脗聝脙聝脗聜脙聜脗聝脙聝脗聝脙聜脗聜脙聝脗聜脙聜脗聜脙聝脗聝脙聜脗聝脙聝脗聜脙聜脗聜脙聝脗聝脙聜脗聜脙聝脗聜脙聜脗聜脙聝脗聝脙聜脗聝脙聝脗聜脙聜脗聝脙聝脗聝脙聜脗聜脙聝脗聜脙聜脗聝脙聝脗聝脙聜脗聝脙聝脗聜脙聜脗聜脙聝脗聝脙聜脗聜脙聝脗聜脙聜脗聝脙聝脗聝脙聜脗聝脙聝脗聜脙聜脗聝脙聝脗聝脙聜脗聜脙聝脗聜脙聜脗聜脙聝脗聝脙聜脗聝脙聝脗聜脙聜脗聜脙聝脗聝脙聜脗聜脙聝脗聜脙聜脗聜脙聝脗聝脙聜脗聝脙聝脗聜脙聜脗聝脙聝脗聝脙聜脗聜脙聝脗聜脙聜脗聝脙聝脗聝脙聜脗聝脙聝脗聜脙聜脗聜脙聝脗聝脙聜脗聜脙聝脗聜脙聜脗聜脙聝脗聝脙聜脗聝脙聝脗聜脙聜脗聝脙聝脗聝脙聜脗聜脙聝脗聜脙聜脗聜脙聝脗聝脙聜脗聝脙聝脗聜脙聜脗聜脙聝脗聝脙聜脗聜脙聝脗聜脙聜脗聜脙聝脗聝脙聜脗聝脙聝脗聜脙聜脗聝脙聝脗聝脙聜脗聜脙聝脗聜脙聜脗聝脙聝脗聝脙聜脗聝脙聝脗聜脙聜脗聜脙聝脗聝脙聜脗聜脙聝脗聜脙聜脗聝脙聝脗聝脙聜脗聝脙聝脗聜脙聜脗聝脙聝脗聝脙聜脗聜脙聝脗聜脙聜脗聜脙聝脗聝脙聜脗聝脙聝脗聜脙聜脗聜脙聝脗聝脙聜脗聜脙聝脗聜脙聜脗聝脙聝脗聝脙聜脗聝脙聝脗聜脙聜脗聝脙聝脗聝脙聜脗聜脙聝脗聜脙聜脗聝脙聝脗聝脙聜脗聝脙聝脗聜脙聜脗聜脙聝脗聝脙聜脗聜脙聝脗聜脙聜脗聜脙聝脗聝脙聜脗聝脙聝脗聜脙聜脗聝脙聝脗聝脙聜脗聜脙聝脗聜脙聜脗聜脙聝脗聝脙聜脗聝脙聝脗聜脙聜脗聜脙聝脗聝脙聜脗聜脙聝脗聜脙聜脗聝脙聝脗聝脙聜脗聝脙聝脗聜脙聜脗聝脙聝脗聝脙聜脗聜脙聝脗聜脙聜脗聝脙聝脗聝脙聜脗聝脙聝脗聜脙聜脗聜脙聝脗聝脙聜脗聜脙聝脗聜脙聜脗聝脙聝脗聝脙聜脗聝脙聝脗聜脙聜脗聝脙聝脗聝脙聜脗聜脙聝脗聜脙聜脗聜脙聝脗聝脙聜脗聝脙聝脗聜脙聜脗聜脙聝脗聝脙聜脗聜脙聝脗聜脙聜脗聜脙聝脗聝脙聜脗聝脙聝脗聜脙聜脗聝脙聝脗聝脙聜脗聜脙聝脗聜脙聜脗聝脙聝脗聝脙聜脗聝脙聝脗聜脙聜脗聜脙聝脗聝脙聜脗聜脙聝脗聜脙聜脗聜脙聝脗聝脙聜脗聝脙聝脗聜脙聜脗聝脙聝脗聝脙聜脗聜脙聝脗聜脙聜脗聜脙聝脗聝脙聜脗聝脙聝脗聜脙聜脗聜脙聝脗聝脙聜脗聜脙聝脗聜脙聜脗聜脙聝脗聝脙聜脗聝脙聝脗聜脙聜脗聝脙聝脗聝脙聜脗聜脙聝脗聜脙聜脗聝脙聝脗聝脙聜脗聝脙聝脗聜脙聜脗聜脙聝脗聝脙聜脗聜脙聝脗聜脙聜脗聝脙聝脗聝脙聜脗聝脙聝脗聜脙聜脗聝脙聝脗聝脙聜脗聜脙聝脗聜脙聜脗聜脙聝脗聝脙聜脗聝脙聝脗聜脙聜脗聜脙聝脗聝脙聜脗聜脙聝脗聜脙聜脗聝脙聝脗聝脙聜脗聝脙聝脗聜脙聜脗聝脙聝脗聝脙聜脗聜脙聝脗聜脙聜脗聝脙聝脗聝脙聜脗聝脙聝脗聜脙聜脗聜脙聝脗聝脙聜脗聜脙聝脗聜脙聜脗聜脙聝脗聝脙聜脗聝脙聝脗聜脙聜脗聝脙聝脗聝脙聜脗聜脙聝脗聜脙聜脗聜脙聝脗聝脙聜脗聝脙聝脗聜脙聜脗聜脙聝脗聝脙聜脗聜脙聝脗聜脙聜脗聜脙聝脗聝脙聜脗聝脙聝脗聜脙聜脗聝脙聝脗聝脙聜脗聜脙聝脗聜脙聜脗聝脙聝脗聝脙聜脗聝脙聝脗聜脙聜脗聜脙聝脗聝脙聜脗聜脙聝脗聜脙聜脗聝脙聝脗聝脙聜脗聝脙聝脗聜脙聜脗聝脙聝脗聝脙聜脗聜脙聝脗聜脙聜脗聜脙聝脗聝脙聜脗聝脙聝脗聜脙聜脗聜脙聝脗聝脙聜脗聜脙聝脗聜脙聜脗聜脙聝脗聝脙聜脗聝脙聝脗聜脙聜脗聝脙聝脗聝脙聜脗聜脙聝脗聜脙聜脗聝脙聝脗聝脙聜脗聝脙聝脗聜脙聜脗聜脙聝脗聝脙聜脗聜脙聝脗聜脙聜脗聜脙聝脗聝脙聜脗聝脙聝脗聜脙聜脗聝脙聝脗聝脙聜脗聜脙聝脗聜脙聜脗聜脙聝脗聝脙聜脗聝脙聝脗聜脙聜脗聜脙聝脗聝脙聜脗聜脙聝脗聜脙聜脗聙脙聝脗聝脙聜脗聝脙聝脗聜脙聜脗聝脙聝脗聝脙聜脗聜脙聝脗聜脙聜脗聝脙聝脗聝脙聜脗聝脙聝脗聜脙聜脗聜脙聝脗聝脙聜脗聜脙聝脗聜脙聜脗聝脙聝脗聝脙聜脗聝脙聝脗聜脙聜脗聝脙聝脗聝脙聜脗聜脙聝脗聜脙聜脗聜脙聝脗聝脙聜脗聝脙聝脗聜脙聜脗聜脙聝脗聝脙聜脗聜脙聝脗聜脙聜脗聝脙聝脗聝脙聜脗聝脙聝脗聜脙聜脗聝脙聝脗聝脙聜脗聜脙聝脗聜脙聜脗聝脙聝脗聝脙聜脗聝脙聝脗聜脙聜脗聜脙聝脗聝脙聜脗聜脙聝脗聜脙聜脗聜脙聝脗聝脙聜脗聝脙聝脗聜脙聜脗聝脙聝脗聝脙聜脗聜脙聝脗聜脙聜脗聜脙聝脗聝脙聜脗聝脙聝脗聜脙聜脗聜脙聝脗聝脙聜脗聜脙聝脗聜脙聜脗聝脙聝脗聝脙聜脗聝脙聝脗聜脙聜脗聝脙聝脗聝脙聜脗聜脙聝脗聜脙聜脗聝脙聝脗聝脙聜脗聝脙聝脗聜脙聜脗聜脙聝脗聝脙聜脗聜脙聝脗聜脙聜脗聝脙聝脗聝脙聜脗聝脙聝脗聜脙聜脗聝脙聝脗聝脙聜脗聜脙聝脗聜脙聜脗聜脙聝脗聝脙聜脗聝脙聝脗聜脙聜脗聜脙聝脗聝脙聜脗聜脙聝脗聜脙聜脗聜脙聝脗聝脙聜脗聝脙聝脗聜脙聜脗聝脙聝脗聝脙聜脗聜脙聝脗聜脙聜脗聝脙聝脗聝脙聜脗聝脙聝脗聜脙聜脗聜脙聝脗聝脙聜脗聜脙聝脗聜脙聜脗聜脙聝脗聝脙聜脗聝脙聝脗聜脙聜脗聝脙聝脗聝脙聜脗聜脙聝脗聜脙聜脗聜脙聝脗聝脙聜脗聝脙聝脗聜脙聜脗聜脙聝脗聝脙聜脗聜脙聝脗聜脙聜脗聝脙聝脗聝脙聜脗聝脙聝脗聜脙聜脗聝脙聝脗聝脙聜脗聜脙聝脗聜脙聜脗聝脙聝脗聝脙聜脗聝脙聝脗聜脙聜脗聜脙聝脗聝脙聜脗聜脙聝脗聜脙聜脗聝脙聝脗聝脙聜脗聝脙聝脗聜脙聜脗聝脙聝脗聝脙聜脗聜脙聝脗聜脙聜脗聜脙聝脗聝脙聜脗聝脙聝脗聜脙聜脗聜脙聝脗聝脙聜脗聜脙聝脗聜脙聜脗聝脙聝脗聝脙聜脗聝脙聝脗聜脙聜脗聝脙聝脗聝脙聜脗聜脙聝脗聜脙聜脗聝脙聝脗聝脙聜脗聝脙聝脗聜脙聜脗聜脙聝脗聝脙聜脗聜脙聝脗聜脙聜脗聜脙聝脗聝脙聜脗聝脙聝脗聜脙聜脗聝脙聝脗聝脙聜脗聜脙聝脗聜脙聜脗聜脙聝脗聝脙聜脗聝脙聝脗聜脙聜脗聜脙聝脗聝脙聜脗聜脙聝脗聜脙聜脗聜脙聝脗聝脙聜脗聝脙聝脗聜脙聜脗聝脙聝脗聝脙聜脗聜脙聝脗聜脙聜脗聝脙聝脗聝脙聜脗聝脙聝脗聜脙聜脗聜脙聝脗聝脙聜脗聜脙聝脗聜脙聜脗聝脙聝脗聝脙聜脗聝脙聝脗聜脙聜脗聝脙聝脗聝脙聜脗聜脙聝脗聜脙聜脗聜脙聝脗聝脙聜脗聝脙聝脗聜脙聜脗聜脙聝脗聝脙聜脗聜脙聝脗聜脙聜脗聜脙聝脗聝脙聜脗聝脙聝脗聜脙聜脗聝脙聝脗聝脙聜脗聜脙聝脗聜脙聜脗聝脙聝脗聝脙聜脗聝脙聝脗聜脙聜脗聜脙聝脗聝脙聜脗聜脙聝脗聜脙聜脗聜脙聝脗聝脙聜脗聝脙聝脗聜脙聜脗聝脙聝脗聝脙聜脗聜脙聝脗聜脙聜脗聜脙聝脗聝脙聜脗聝脙聝脗聜脙聜脗聜脙聝脗聝脙聜脗聜脙聝脗聜脙聜脗聜脙聝脗聝脙聜脗聝脙聝脗聜脙聜脗聝脙聝脗聝脙聜脗聜脙聝脗聜脙聜脗聝脙聝脗聝脙聜脗聝脙聝脗聜脙聜脗聜脙聝脗聝脙聜脗聜脙聝脗聜脙聜脗聝脙聝脗聝脙聜脗聝脙聝脗聜脙聜脗聝脙聝脗聝脙聜脗聜脙聝脗聜脙聜脗聜脙聝脗聝脙聜脗聝脙聝脗聜脙聜脗聜脙聝脗聝脙聜脗聜脙聝脗聜脙聜脗聝脙聝脗聝脙聜脗聝脙聝脗聜脙聜脗聝脙聝脗聝脙聜脗聜脙聝脗聜脙聜脗聝脙聝脗聝脙聜脗聝脙聝脗聜脙聜脗聜脙聝脗聝脙聜脗聜脙聝脗聜脙聜脗聜脙聝脗聝脙聜脗聝脙聝脗聜脙聜脗聝脙聝脗聝脙聜脗聜脙聝脗聜脙聜脗聜脙聝脗聝脙聜脗聝脙聝脗聜脙聜脗聜脙聝脗聝脙聜脗聜脙聝脗聜脙聜脗聝脙聝脗聝脙聜脗聝脙聝脗聜脙聜脗聝脙聝脗聝脙聜脗聜脙聝脗聜脙聜脗聝脙聝脗聝脙聜脗聝脙聝脗聜脙聜脗聜脙聝脗聝脙聜脗聜脙聝脗聜脙聜脗聝脙聝脗聝脙聜脗聝脙聝脗聜脙聜脗聝脙聝脗聝脙聜脗聜脙聝脗聜脙聜脗聜脙聝脗聝脙聜脗聝脙聝脗聜脙聜脗聜脙聝脗聝脙聜脗聜脙聝脗聜脙聜脗聜脙聝脗聝脙聜脗聝脙聝脗聜脙聜脗聝脙聝脗聝脙聜脗聜脙聝脗聜脙聜脗聝脙聝脗聝脙聜脗聝脙聝脗聜脙聜脗聜脙聝脗聝脙聜脗聜脙聝脗聜脙聜脗聜脙聝脗聝脙聜脗聝脙聝脗聜脙聜脗聝脙聝脗聝脙聜脗聜脙聝脗聜脙聜脗聜脙聝脗聝脙聜脗聝脙聝脗聜脙聜脗聜脙聝脗聝脙聜脗聜脙聝脗聜脙聜脗聜脙聝脗聝脙聜脗聝脙聝脗聜脙聜脗聝脙聝脗聝脙聜脗聜脙聝脗聜脙聜脗聝脙聝脗聝脙聜脗聝脙聝脗聜脙聜脗聜脙聝脗聝脙聜脗聜脙聝脗聜脙聜脗聝脙聝脗聝脙聜脗聝脙聝脗聜脙聜脗聝脙聝脗聝脙聜脗聜脙聝脗聜脙聜脗聜脙聝脗聝脙聜脗聝脙聝脗聜脙聜脗聜脙聝脗聝脙聜脗聜脙聝脗聜脙聜脗聝脙聝脗聝脙聜脗聝脙聝脗聜脙聜脗聝脙聝脗聝脙聜脗聜脙聝脗聜脙聜脗聝脙聝脗聝脙聜脗聝脙聝脗聜脙聜脗聜脙聝脗聝脙聜脗聜脙聝脗聜脙聜脗聜脙聝脗聝脙聜脗聝脙聝脗聜脙聜脗聝脙聝脗聝脙聜脗聜脙聝脗聜脙聜脗聜脙聝脗聝脙聜脗聝脙聝脗聜脙聜脗聜脙聝脗聝脙聜脗聜脙聝脗聜脙聜脗聜脙聝脗聝脙聜脗聝脙聝脗聜脙聜脗聝脙聝脗聝脙聜脗聜脙聝脗聜脙聜脗聝脙聝脗聝脙聜脗聝脙聝脗聜脙聜脗聜脙聝脗聝脙聜脗聜脙聝脗聜脙聜脗聝脙聝脗聝脙聜脗聝脙聝脗聜脙聜脗聝脙聝脗聝脙聜脗聜脙聝脗聜脙聜脗聜脙聝脗聝脙聜脗聝脙聝脗聜脙聜脗聜脙聝脗聝脙聜脗聜脙聝脗聜脙聜脗聜脙聝脗聝脙聜脗聝脙聝脗聜脙聜脗聝脙聝脗聝脙聜脗聜脙聝脗聜脙聜脗聝脙聝脗聝脙聜脗聝脙聝脗聜脙聜脗聜脙聝脗聝脙聜脗聜脙聝脗聜脙聜脗聜脙聝脗聝脙聜脗聝脙聝脗聜脙聜脗聝脙聝脗聝脙聜脗聜脙聝脗聜脙聜脗聜脙聝脗聝脙聜脗聝脙聝脗聜脙聜脗聜脙聝脗聝脙聜脗聜脙聝脗聜脙聜脗聺 - Mordin Solus"
  },
  {
    "id": 452638,
    "slug": "stray-2",
    "title": "Stray",
    "year": 2022,
    "coverImage": "https://media.rawg.io/media/games/cd3/cd3c9c7d3e95cb1608fd6250f1b90b7a.jpg",
    "rawgUrl": "https://rawg.io/games/stray-2",
    "genres": [
      "Adventure",
      "Action",
      "Puzzle",
      "Indie",
      "Platformer"
    ],
    "metacritic": 82,
    "played": true,
    "platform": "PS5",
    "platformType": "PlayStation",
    "datePlayed": "2023-11",
    "completionStatus": "Completed",
    "rating": 10,
    "description": "Loved it. Amazing to play as a cat. Excellent!"
  },
  {
    "id": 438620,
    "slug": "the-lord-of-the-rings-gollum",
    "title": "The Lord of the Rings: Gollum",
    "year": 2023,
    "coverImage": "https://media.rawg.io/media/games/470/470fb8435cdea25bda1126e0b8e0a3b0.jpg",
    "rawgUrl": "https://rawg.io/games/the-lord-of-the-rings-gollum",
    "genres": [
      "Adventure",
      "Action",
      "RPG"
    ],
    "metacritic": 40,
    "played": true,
    "platform": "PS5",
    "platformType": "PlayStation",
    "datePlayed": "2023-11",
    "completionStatus": "Dropped",
    "rating": 1,
    "description": "Too bad such a good concept and game was wasted by poor execution. If it didn脙聝脗聝脙聜脗聝脙聝脗聜脙聜脗聝脙聝脗聝脙聜脗聜脙聝脗聜脙聜脗聝脙聝脗聝脙聜脗聝脙聝脗聜脙聜脗聜脙聝脗聝脙聜脗聜脙聝脗聜脙聜脗聝脙聝脗聝脙聜脗聝脙聝脗聜脙聜脗聝脙聝脗聝脙聜脗聜脙聝脗聜脙聜脗聜脙聝脗聝脙聜脗聝脙聝脗聜脙聜脗聜脙聝脗聝脙聜脗聜脙聝脗聜脙聜脗聝脙聝脗聝脙聜脗聝脙聝脗聜脙聜脗聝脙聝脗聝脙聜脗聜脙聝脗聜脙聜脗聝脙聝脗聝脙聜脗聝脙聝脗聜脙聜脗聜脙聝脗聝脙聜脗聜脙聝脗聜脙聜脗聜脙聝脗聝脙聜脗聝脙聝脗聜脙聜脗聝脙聝脗聝脙聜脗聜脙聝脗聜脙聜脗聜脙聝脗聝脙聜脗聝脙聝脗聜脙聜脗聜脙聝脗聝脙聜脗聜脙聝脗聜脙聜脗聝脙聝脗聝脙聜脗聝脙聝脗聜脙聜脗聝脙聝脗聝脙聜脗聜脙聝脗聜脙聜脗聝脙聝脗聝脙聜脗聝脙聝脗聜脙聜脗聜脙聝脗聝脙聜脗聜脙聝脗聜脙聜脗聝脙聝脗聝脙聜脗聝脙聝脗聜脙聜脗聝脙聝脗聝脙聜脗聜脙聝脗聜脙聜脗聜脙聝脗聝脙聜脗聝脙聝脗聜脙聜脗聜脙聝脗聝脙聜脗聜脙聝脗聜脙聜脗聜脙聝脗聝脙聜脗聝脙聝脗聜脙聜脗聝脙聝脗聝脙聜脗聜脙聝脗聜脙聜脗聝脙聝脗聝脙聜脗聝脙聝脗聜脙聜脗聜脙聝脗聝脙聜脗聜脙聝脗聜脙聜脗聜脙聝脗聝脙聜脗聝脙聝脗聜脙聜脗聝脙聝脗聝脙聜脗聜脙聝脗聜脙聜脗聜脙聝脗聝脙聜脗聝脙聝脗聜脙聜脗聜脙聝脗聝脙聜脗聜脙聝脗聜脙聜脗垄脙聝脗聝脙聜脗聝脙聝脗聜脙聜脗聝脙聝脗聝脙聜脗聜脙聝脗聜脙聜脗聝脙聝脗聝脙聜脗聝脙聝脗聜脙聜脗聜脙聝脗聝脙聜脗聜脙聝脗聜脙聜脗聝脙聝脗聝脙聜脗聝脙聝脗聜脙聜脗聝脙聝脗聝脙聜脗聜脙聝脗聜脙聜脗聜脙聝脗聝脙聜脗聝脙聝脗聜脙聜脗聜脙聝脗聝脙聜脗聜脙聝脗聜脙聜脗聝脙聝脗聝脙聜脗聝脙聝脗聜脙聜脗聝脙聝脗聝脙聜脗聜脙聝脗聜脙聜脗聝脙聝脗聝脙聜脗聝脙聝脗聜脙聜脗聜脙聝脗聝脙聜脗聜脙聝脗聜脙聜脗聜脙聝脗聝脙聜脗聝脙聝脗聜脙聜脗聝脙聝脗聝脙聜脗聜脙聝脗聜脙聜脗聜脙聝脗聝脙聜脗聝脙聝脗聜脙聜脗聜脙聝脗聝脙聜脗聜脙聝脗聜脙聜脗聜脙聝脗聝脙聜脗聝脙聝脗聜脙聜脗聝脙聝脗聝脙聜脗聜脙聝脗聜脙聜脗聝脙聝脗聝脙聜脗聝脙聝脗聜脙聜脗聜脙聝脗聝脙聜脗聜脙聝脗聜脙聜脗聝脙聝脗聝脙聜脗聝脙聝脗聜脙聜脗聝脙聝脗聝脙聜脗聜脙聝脗聜脙聜脗聜脙聝脗聝脙聜脗聝脙聝脗聜脙聜脗聜脙聝脗聝脙聜脗聜脙聝脗聜脙聜脗聜脙聝脗聝脙聜脗聝脙聝脗聜脙聜脗聝脙聝脗聝脙聜脗聜脙聝脗聜脙聜脗聝脙聝脗聝脙聜脗聝脙聝脗聜脙聜脗聜脙聝脗聝脙聜脗聜脙聝脗聜脙聜脗聜脙聝脗聝脙聜脗聝脙聝脗聜脙聜脗聝脙聝脗聝脙聜脗聜脙聝脗聜脙聜脗聜脙聝脗聝脙聜脗聝脙聝脗聜脙聜脗聜脙聝脗聝脙聜脗聜脙聝脗聜脙聜脗聙脙聝脗聝脙聜脗聝脙聝脗聜脙聜脗聝脙聝脗聝脙聜脗聜脙聝脗聜脙聜脗聝脙聝脗聝脙聜脗聝脙聝脗聜脙聜脗聜脙聝脗聝脙聜脗聜脙聝脗聜脙聜脗聝脙聝脗聝脙聜脗聝脙聝脗聜脙聜脗聝脙聝脗聝脙聜脗聜脙聝脗聜脙聜脗聜脙聝脗聝脙聜脗聝脙聝脗聜脙聜脗聜脙聝脗聝脙聜脗聜脙聝脗聜脙聜脗聝脙聝脗聝脙聜脗聝脙聝脗聜脙聜脗聝脙聝脗聝脙聜脗聜脙聝脗聜脙聜脗聝脙聝脗聝脙聜脗聝脙聝脗聜脙聜脗聜脙聝脗聝脙聜脗聜脙聝脗聜脙聜脗聜脙聝脗聝脙聜脗聝脙聝脗聜脙聜脗聝脙聝脗聝脙聜脗聜脙聝脗聜脙聜脗聜脙聝脗聝脙聜脗聝脙聝脗聜脙聜脗聜脙聝脗聝脙聜脗聜脙聝脗聜脙聜脗聜脙聝脗聝脙聜脗聝脙聝脗聜脙聜脗聝脙聝脗聝脙聜脗聜脙聝脗聜脙聜脗聝脙聝脗聝脙聜脗聝脙聝脗聜脙聜脗聜脙聝脗聝脙聜脗聜脙聝脗聜脙聜脗聝脙聝脗聝脙聜脗聝脙聝脗聜脙聜脗聝脙聝脗聝脙聜脗聜脙聝脗聜脙聜脗聜脙聝脗聝脙聜脗聝脙聝脗聜脙聜脗聜脙聝脗聝脙聜脗聜脙聝脗聜脙聜脗聜脙聝脗聝脙聜脗聝脙聝脗聜脙聜脗聝脙聝脗聝脙聜脗聜脙聝脗聜脙聜脗聝脙聝脗聝脙聜脗聝脙聝脗聜脙聜脗聜脙聝脗聝脙聜脗聜脙聝脗聜脙聜脗聜脙聝脗聝脙聜脗聝脙聝脗聜脙聜脗聝脙聝脗聝脙聜脗聜脙聝脗聜脙聜脗聜脙聝脗聝脙聜脗聝脙聝脗聜脙聜脗聜脙聝脗聝脙聜脗聜脙聝脗聜脙聜脗聶t keep glitching and forcing me to restart, I脙聝脗聝脙聜脗聝脙聝脗聜脙聜脗聝脙聝脗聝脙聜脗聜脙聝脗聜脙聜脗聝脙聝脗聝脙聜脗聝脙聝脗聜脙聜脗聜脙聝脗聝脙聜脗聜脙聝脗聜脙聜脗聝脙聝脗聝脙聜脗聝脙聝脗聜脙聜脗聝脙聝脗聝脙聜脗聜脙聝脗聜脙聜脗聜脙聝脗聝脙聜脗聝脙聝脗聜脙聜脗聜脙聝脗聝脙聜脗聜脙聝脗聜脙聜脗聝脙聝脗聝脙聜脗聝脙聝脗聜脙聜脗聝脙聝脗聝脙聜脗聜脙聝脗聜脙聜脗聝脙聝脗聝脙聜脗聝脙聝脗聜脙聜脗聜脙聝脗聝脙聜脗聜脙聝脗聜脙聜脗聜脙聝脗聝脙聜脗聝脙聝脗聜脙聜脗聝脙聝脗聝脙聜脗聜脙聝脗聜脙聜脗聜脙聝脗聝脙聜脗聝脙聝脗聜脙聜脗聜脙聝脗聝脙聜脗聜脙聝脗聜脙聜脗聝脙聝脗聝脙聜脗聝脙聝脗聜脙聜脗聝脙聝脗聝脙聜脗聜脙聝脗聜脙聜脗聝脙聝脗聝脙聜脗聝脙聝脗聜脙聜脗聜脙聝脗聝脙聜脗聜脙聝脗聜脙聜脗聝脙聝脗聝脙聜脗聝脙聝脗聜脙聜脗聝脙聝脗聝脙聜脗聜脙聝脗聜脙聜脗聜脙聝脗聝脙聜脗聝脙聝脗聜脙聜脗聜脙聝脗聝脙聜脗聜脙聝脗聜脙聜脗聜脙聝脗聝脙聜脗聝脙聝脗聜脙聜脗聝脙聝脗聝脙聜脗聜脙聝脗聜脙聜脗聝脙聝脗聝脙聜脗聝脙聝脗聜脙聜脗聜脙聝脗聝脙聜脗聜脙聝脗聜脙聜脗聜脙聝脗聝脙聜脗聝脙聝脗聜脙聜脗聝脙聝脗聝脙聜脗聜脙聝脗聜脙聜脗聜脙聝脗聝脙聜脗聝脙聝脗聜脙聜脗聜脙聝脗聝脙聜脗聜脙聝脗聜脙聜脗垄脙聝脗聝脙聜脗聝脙聝脗聜脙聜脗聝脙聝脗聝脙聜脗聜脙聝脗聜脙聜脗聝脙聝脗聝脙聜脗聝脙聝脗聜脙聜脗聜脙聝脗聝脙聜脗聜脙聝脗聜脙聜脗聝脙聝脗聝脙聜脗聝脙聝脗聜脙聜脗聝脙聝脗聝脙聜脗聜脙聝脗聜脙聜脗聜脙聝脗聝脙聜脗聝脙聝脗聜脙聜脗聜脙聝脗聝脙聜脗聜脙聝脗聜脙聜脗聝脙聝脗聝脙聜脗聝脙聝脗聜脙聜脗聝脙聝脗聝脙聜脗聜脙聝脗聜脙聜脗聝脙聝脗聝脙聜脗聝脙聝脗聜脙聜脗聜脙聝脗聝脙聜脗聜脙聝脗聜脙聜脗聜脙聝脗聝脙聜脗聝脙聝脗聜脙聜脗聝脙聝脗聝脙聜脗聜脙聝脗聜脙聜脗聜脙聝脗聝脙聜脗聝脙聝脗聜脙聜脗聜脙聝脗聝脙聜脗聜脙聝脗聜脙聜脗聜脙聝脗聝脙聜脗聝脙聝脗聜脙聜脗聝脙聝脗聝脙聜脗聜脙聝脗聜脙聜脗聝脙聝脗聝脙聜脗聝脙聝脗聜脙聜脗聜脙聝脗聝脙聜脗聜脙聝脗聜脙聜脗聝脙聝脗聝脙聜脗聝脙聝脗聜脙聜脗聝脙聝脗聝脙聜脗聜脙聝脗聜脙聜脗聜脙聝脗聝脙聜脗聝脙聝脗聜脙聜脗聜脙聝脗聝脙聜脗聜脙聝脗聜脙聜脗聜脙聝脗聝脙聜脗聝脙聝脗聜脙聜脗聝脙聝脗聝脙聜脗聜脙聝脗聜脙聜脗聝脙聝脗聝脙聜脗聝脙聝脗聜脙聜脗聜脙聝脗聝脙聜脗聜脙聝脗聜脙聜脗聜脙聝脗聝脙聜脗聝脙聝脗聜脙聜脗聝脙聝脗聝脙聜脗聜脙聝脗聜脙聜脗聜脙聝脗聝脙聜脗聝脙聝脗聜脙聜脗聜脙聝脗聝脙聜脗聜脙聝脗聜脙聜脗聙脙聝脗聝脙聜脗聝脙聝脗聜脙聜脗聝脙聝脗聝脙聜脗聜脙聝脗聜脙聜脗聝脙聝脗聝脙聜脗聝脙聝脗聜脙聜脗聜脙聝脗聝脙聜脗聜脙聝脗聜脙聜脗聝脙聝脗聝脙聜脗聝脙聝脗聜脙聜脗聝脙聝脗聝脙聜脗聜脙聝脗聜脙聜脗聜脙聝脗聝脙聜脗聝脙聝脗聜脙聜脗聜脙聝脗聝脙聜脗聜脙聝脗聜脙聜脗聝脙聝脗聝脙聜脗聝脙聝脗聜脙聜脗聝脙聝脗聝脙聜脗聜脙聝脗聜脙聜脗聝脙聝脗聝脙聜脗聝脙聝脗聜脙聜脗聜脙聝脗聝脙聜脗聜脙聝脗聜脙聜脗聜脙聝脗聝脙聜脗聝脙聝脗聜脙聜脗聝脙聝脗聝脙聜脗聜脙聝脗聜脙聜脗聜脙聝脗聝脙聜脗聝脙聝脗聜脙聜脗聜脙聝脗聝脙聜脗聜脙聝脗聜脙聜脗聜脙聝脗聝脙聜脗聝脙聝脗聜脙聜脗聝脙聝脗聝脙聜脗聜脙聝脗聜脙聜脗聝脙聝脗聝脙聜脗聝脙聝脗聜脙聜脗聜脙聝脗聝脙聜脗聜脙聝脗聜脙聜脗聝脙聝脗聝脙聜脗聝脙聝脗聜脙聜脗聝脙聝脗聝脙聜脗聜脙聝脗聜脙聜脗聜脙聝脗聝脙聜脗聝脙聝脗聜脙聜脗聜脙聝脗聝脙聜脗聜脙聝脗聜脙聜脗聜脙聝脗聝脙聜脗聝脙聝脗聜脙聜脗聝脙聝脗聝脙聜脗聜脙聝脗聜脙聜脗聝脙聝脗聝脙聜脗聝脙聝脗聜脙聜脗聜脙聝脗聝脙聜脗聜脙聝脗聜脙聜脗聜脙聝脗聝脙聜脗聝脙聝脗聜脙聜脗聝脙聝脗聝脙聜脗聜脙聝脗聜脙聜脗聜脙聝脗聝脙聜脗聝脙聝脗聜脙聜脗聜脙聝脗聝脙聜脗聜脙聝脗聜脙聜脗聶d still be playing it as a fan of the Middle Earth and stealth games."
  },
  {
    "id": 28,
    "slug": "red-dead-redemption-2",
    "title": "Red Dead Redemption 2",
    "year": 2018,
    "coverImage": "https://media.rawg.io/media/games/511/5118aff5091cb3efec399c808f8c598f.jpg",
    "rawgUrl": "https://rawg.io/games/red-dead-redemption-2",
    "genres": [
      "Action"
    ],
    "metacritic": 96,
    "played": true,
    "platform": "PS5",
    "platformType": "PlayStation",
    "datePlayed": "2023-12",
    "completionStatus": "Completed",
    "rating": 10,
    "description": "Amazing game. The beginning is a bit slow, but it becomes excellent. A vast world, strong characters, and a beautiful, emotional story."
  },
  {
    "id": 18240,
    "slug": "brothers-a-tale-of-two-sons-2",
    "title": "Brothers: A Tale of Two Sons",
    "year": 2013,
    "coverImage": "https://media.rawg.io/media/games/b6b/b6b20bfc4b34e312dbc8aac53c95a348.jpg",
    "rawgUrl": "https://rawg.io/games/brothers-a-tale-of-two-sons-2",
    "genres": [
      "Indie",
      "Adventure",
      "Action"
    ],
    "metacritic": 90,
    "played": true,
    "platform": "PS5",
    "platformType": "PlayStation",
    "datePlayed": "2023-12",
    "completionStatus": "Completed",
    "rating": 10,
    "description": "Another beautiful, emotional game. Unfortunately, it was too short."
  },
  {
    "id": 29177,
    "slug": "detroit-become-human",
    "title": "Detroit: Become Human",
    "year": 2018,
    "coverImage": "https://media.rawg.io/media/games/951/951572a3dd1e42544bd39a5d5b42d234.jpg",
    "rawgUrl": "https://rawg.io/games/detroit-become-human",
    "genres": [
      "Adventure",
      "Action"
    ],
    "metacritic": 79,
    "played": true,
    "platform": "PS5",
    "platformType": "PlayStation",
    "datePlayed": "2023-12",
    "completionStatus": "Completed",
    "rating": 10,
    "description": "Great game. I loved the story and how choices mattered. It made me think a lot about AI and robotics. 脙聝脗聝脙聜脗聝脙聝脗聜脙聜脗聝脙聝脗聝脙聜脗聜脙聝脗聜脙聜脗聝脙聝脗聝脙聜脗聝脙聝脗聜脙聜脗聜脙聝脗聝脙聜脗聜脙聝脗聜脙聜脗垄脙聝脗聝脙聜脗聝脙聝脗聜脙聜脗聝脙聝脗聝脙聜脗聜脙聝脗聜脙聜脗聜脙聝脗聝脙聜脗聝脙聝脗聜脙聜脗聜脙聝脗聝脙聜脗聜脙聝脗聜脙聜脗聹脙聝脗聝脙聜脗聝脙聝脗聜脙聜脗聝脙聝脗聝脙聜脗聜脙聝脗聜脙聜脗聜脙聝脗聝脙聜脗聝脙聝脗聜脙聜脗聜脙聝脗聝脙聜脗聜脙聝脗聜脙聜脗聤"
  },
  {
    "id": 324997,
    "slug": "baldurs-gate-3",
    "title": "Baldur's Gate III",
    "year": 2023,
    "coverImage": "https://media.rawg.io/media/games/699/69907ecf13f172e9e144069769c3be73.jpg",
    "rawgUrl": "https://rawg.io/games/baldurs-gate-3",
    "genres": [
      "Strategy",
      "Adventure",
      "RPG"
    ],
    "metacritic": 97,
    "played": false,
    "platform": null,
    "platformType": null,
    "datePlayed": null,
    "completionStatus": null,
    "rating": null,
    "description": null
  },
  {
    "id": 326243,
    "slug": "elden-ring",
    "title": "Elden Ring",
    "year": 2022,
    "coverImage": "https://media.rawg.io/media/games/b29/b294fdd866dcdb643e7bab370a552855.jpg",
    "rawgUrl": "https://rawg.io/games/elden-ring",
    "genres": [
      "Action",
      "RPG"
    ],
    "metacritic": 95,
    "played": false,
    "platform": null,
    "platformType": null,
    "datePlayed": null,
    "completionStatus": null,
    "rating": null,
    "description": null
  },
  {
    "id": 997548,
    "slug": "elden-ring-nightreign",
    "title": "Elden Ring Nightreign",
    "year": 2025,
    "coverImage": "https://media.rawg.io/media/games/a14/a143ef815d323a3000840fc774d834c7.jpg",
    "rawgUrl": "https://rawg.io/games/elden-ring-nightreign",
    "genres": [
      "Action",
      "RPG"
    ],
    "metacritic": null,
    "played": false,
    "platform": null,
    "platformType": null,
    "datePlayed": null,
    "completionStatus": null,
    "rating": null,
    "description": null
  },
  {
    "id": 799265,
    "slug": "the-last-of-us-part-i",
    "title": "The Last of Us Part I",
    "year": 2022,
    "coverImage": "https://media.rawg.io/media/games/71d/71df9e759b2246f9769126c98ac997fc.jpg",
    "rawgUrl": "https://rawg.io/games/the-last-of-us-part-i",
    "genres": [
      "Shooter",
      "Adventure",
      "Action"
    ],
    "metacritic": null,
    "played": false,
    "platform": null,
    "platformType": null,
    "datePlayed": null,
    "completionStatus": null,
    "rating": null,
    "description": null
  },
  {
    "id": 529698,
    "slug": "the-calisto-protocol",
    "title": "The Callisto Protocol",
    "year": 2022,
    "coverImage": "https://media.rawg.io/media/games/605/605e0c04ba48ece4b4ae7825473477f6.jpg",
    "rawgUrl": "https://rawg.io/games/the-calisto-protocol",
    "genres": [
      "Adventure",
      "Action"
    ],
    "metacritic": 69,
    "played": true,
    "platform": "PS5",
    "platformType": "PlayStation",
    "datePlayed": "2023-12",
    "completionStatus": "Completed",
    "rating": 9,
    "description": "Loved it's jump scares. Great graphics, map, level design, and gameplay."
  },
  {
    "id": 58812,
    "slug": "control",
    "title": "Control",
    "year": 2019,
    "coverImage": "https://media.rawg.io/media/games/253/2534a46f3da7fa7c315f1387515ca393.jpg",
    "rawgUrl": "https://rawg.io/games/control",
    "genres": [
      "Shooter",
      "Adventure",
      "Action"
    ],
    "metacritic": 84,
    "played": true,
    "platform": "PS5",
    "platformType": "PlayStation",
    "datePlayed": "2023-12",
    "completionStatus": "Completed",
    "rating": 6,
    "description": "Loved the puzzles but not a fan of the game overall."
  },
  {
    "id": 2574,
    "slug": "enter-the-gungeon",
    "title": "Enter the Gungeon",
    "year": 2016,
    "coverImage": "https://media.rawg.io/media/games/3be/3be0e624424d3453005019799a760af2.jpg",
    "rawgUrl": "https://rawg.io/games/enter-the-gungeon",
    "genres": [
      "Shooter",
      "Indie",
      "Action"
    ],
    "metacritic": 84,
    "played": true,
    "platform": "PS5",
    "platformType": "PlayStation",
    "datePlayed": "2024-01",
    "completionStatus": "Completed",
    "rating": 3,
    "description": "Not my type or I didn't give it enough chance."
  },
  {
    "id": 4491,
    "slug": "shadow-of-the-colossus",
    "title": "Shadow of the Colossus (2011)",
    "year": 2011,
    "coverImage": "https://media.rawg.io/media/games/6ac/6ac602e70c837ababdf025e997391d9c.jpg",
    "rawgUrl": "https://rawg.io/games/shadow-of-the-colossus",
    "genres": [
      "Action"
    ],
    "metacritic": 91,
    "played": true,
    "platform": "PS5",
    "platformType": "PlayStation",
    "datePlayed": "2023-05",
    "completionStatus": "Completed",
    "rating": 9,
    "description": "A unique experience."
  },
  {
    "id": 1152,
    "slug": "thumper",
    "title": "Thumper",
    "year": 2016,
    "coverImage": "https://media.rawg.io/media/screenshots/f79/f7984b1ef834dac1262382c75adf6a87.jpg",
    "rawgUrl": "https://rawg.io/games/thumper",
    "genres": [
      "Indie",
      "Action"
    ],
    "metacritic": 85,
    "played": true,
    "platform": "PS5",
    "platformType": "PlayStation",
    "datePlayed": "2023-05",
    "completionStatus": "Dropped",
    "rating": 6,
    "description": "Not bad but I didn't find myself coming back to it much."
  }
]
